Workbook

Sheet Ideas
A2: S.no | B2: Tasks | C2: Due date
A3: 1 | B3: Performance Tracking | C3: 05.08.2025
A4: 2 | B4: Deployment of Excess Cash on Books
A5: 3 | B5: New Strategies/Equities Deployment Plan
B6: a. Drawdown Deployment Plan for Equities
B7: b. Leverage using Gold and Equities: QAW at 2x
B8: c. Equity Futures using some leverage since margin is empty
B9: d. Consider tax numbers in all calculations
B10: e. Work Backwards: what needs to be done to make more
A11: 4 | B11: Working Capital Debt on Portfolio
A12: 5 | B12: Deployment in Nasdaq using broker dealer strucutre and grd
A13: 6 | B13: Open IB Tws USA account
A14: 7 | B14: Gold at 2x using Trend Following system
A15: 8 | B15: Equities at 2x using Trend Following System: 10 stock Momentum Portfolio

Sheet Balance Sheet RN
A2: Balance Sheet As on 30.06.2025
A3: S.no | B3: Particulars | C3: Category | D3: 30.06.2025 | F3: S.no | G3: Particulars | H3: Category | I3: 30.06.2025
A4: 1 | B4: Rishabh Nahar | C4: Equity | D4: =31920540+47157270-17646683+4440957-1985702 -> 63886382 | F4: 1 | G4: MCPL | H4: Investment | I4: 28950000
A5: =A4+1 -> 2 | B5: Ramesh Nahar | C5: Equity | D5: 113270120 | F5: =F4+1 -> 2 | G5: Zerodha Total RN | H5: Investment | I5: 44982541
A6: =A5+1 -> 3 | B6: Sushila Nahar | C6: Equity | D6: 41674608 | F6: =F5+1 -> 3 | G6: Zerodha Loaned MCPL | H6: Investment | I6: 189449437
A7: =A6+1 -> 4 | B7: Equity Loans | C7: Equity | D7: 80000000 | F7: =F6+1 -> 4 | G7: Zerodha Loan MCPL Eq | H7: Investment | I7: 16481200
A8: =A7+1 -> 5 | B8: Personal Loans | C8: Debt | D8: 0 | F8: =F7+1 -> 5 | G8: Qode Advisors LLP | H8: Investment | I8: 17500000
A9: =A8+1 -> 6 | B9: Current Year Profits RN | C9: Equity | D9: =-333918+265866 -> -68052 | F9: =F8+1 -> 6 | G9: Qode Securitites | I9: 2051670
A10: =A9+1 -> 7 | B10: Unrelealised Profits RN | C10: Equity | D10: =1692377+18866254 -> 20558631 | F10: =F9+1 -> 7 | G10: Rekha Kothari | H10: Investment | I10: 6750000
A11: =A10+1 -> 8 | B11: Swan | C11: Loan | D11: 6892535 | F11: =F10+1 -> 8 | G11: Sailesh Nahar | H11: Loan | I11: 150000
A12: =A11+1 -> 9 | B12: Less: Tax( SA + Advance) | D12: -7800000 | F12: =F11+1 -> 9 | G12: Qode Advisors PMS | H12: Investment | I12: 7000000
A13: =A12+1 -> 10 | B13: Yogita Gift | D13: -2550000 | F13: =F12+1 -> 10 | G13: Ware Innovations | I13: -158000
A14: 11 | B14: Jainam Nimai Loss | D14: -6113397
D21: =SUM(D4:D19) -> 309750827 | I21: =SUM(I4:I19) -> 313156848 | J21: =D21-I21 -> -3406021

Sheet Balance Sheet MCL
A2: Balance Sheet As on 30.06.2025
A3: S.no | B3: Particulars | C3: Category | D3: 30.06.2025 | F3: S.no | G3: Particulars | H3: Category | I3: 30.06.2025
A4: 1 | B4: Company Capital | C4: Equity | D4: =16588264+12257627-758271 -> 28087620 | F4: 1
A5: =A4+1 -> 2 | B5: Rishabh Nahar | C5: Loan Ac | D5: ='[1]Balance Sheet RN'!I4 -> 28950000 | F5: =F4+1 -> 2 | G5: Zerodha Total MCPL | H5: Investment | I5: =276135000-'[1]Balance Sheet RN'!I6-'[1]Balance Sheet RN'!I7 -> 70204363
A6: =A5+1 -> 3 | B6: Ramesh Nahar | C6: Capital | D6: 25000 | F6: =F5+1 -> 3 | G6: Aurus Alpha LLP | H6: Investment | I6: 44000000
A7: =A6+1 -> 4 | B7: Sushila Nahar | C7: Equity | D7: 25000 | F7: =F6+1 -> 4 | G7: SPF Debtors | I7: 2360000
A8: =A7+1 -> 5 | B8: Rishabh Nahar Capital | C8: Capital | D8: 50000 | F8: =F7+1 -> 5 | G8: Bank Balance
A9: =A8+1 -> 6 | B9: Personal Loans | C9: Debt | D9: 0 | F9: =F8+1 -> 6
A10: =A9+1 -> 7 | B10: Unrealised Profits MCL | C10: Equity | D10: 48000000 | F10: =F9+1 -> 7
A11: =A10+1 -> 8 | B11: Unrelealised Profits MCL | C11: Equity | D11: =1336905 -> 1336905 | F11: =F10+1 -> 8
A12: =A11+1 -> 9 | B12: Consultancy Income CY | C12: Equity | D12: 8000000 | F12: =F11+1 -> 9
A13: =A12+1 -> 10 | B13: Less: Tax( SA + Advance) | D13: =-2000000-1500000 -> -3500000 | F13: =F12+1 -> 10
A14: 11 | F14: 11
A15: 12 | F15: 12
D21: =SUM(D4:D19) -> 110974525 | I21: =SUM(I4:I19) -> 116564363 | K21: =I21-D21 -> 5589838
D26: =D21-D5 -> 82024525

Sheet Pivot
A1: Networth | F1: Equity / Debt / Gold Backed Debt / Cash | AE1: Portfolio Risk
A3: Liquidity | B3: ='Networth Inputs - old'!Q4 -> 8.9887254e+08 | C3: =B3/$B$5 -> 1.081191
A4: Less: Debt | B4: ='Networth Inputs - old'!Q5 -> 67500000 | C4: =B4/$B$5 -> 0.081191038
A5: Networth | B5: ='Networth Inputs - old'!Q6 -> 8.3137254e+08 | Z5: Assets Owned Directly/Indirectly | AE5: Equity | AJ5: Debt
Z7: Equity | AA7: =VLOOKUP("Equity",$P$3:$Q$9,2,FALSE) -> #N/A | AB7: =AA7/$AA$11 -> #N/A | AE7: Zerodha Broking RN: EQ Holdings | AF7: =VLOOKUP(AE7,'Networth Inputs - old'!$C$4:$E$53,3,FALSE) -> 86524104 | AG7: =AF7/$AF$18 -> #N/A | AJ7: Karan SPF | AK7: =VLOOKUP(AJ7,'Networth Inputs - old'!$C$4:$E$53,3,FALSE) -> #N/A | AL7: =AK7/$AK$26 -> #N/A
Z8: Debt | AE8: Zerodha Broking RN: EQ Mutual Funds | AF8: =VLOOKUP(AE8,'Networth Inputs - old'!$C$4:$E$53,3,FALSE) -> 0 | AG8: =AF8/$AF$18 -> #N/A | AJ8: Loan to Vihaan | AK8: =VLOOKUP(AJ8,'Networth Inputs - old'!$C$4:$E$53,3,FALSE) -> 3000000 | AL8: =AK8/$AK$26 -> #N/A
Z9: Gold - India | AA9: =17*100*97873 -> 166384100 | AB9: =AA9/$AA$11 -> #N/A | AE9: Zerodha Broking RN: Cash | AF9: =VLOOKUP(AE9,'Networth Inputs - old'!$C$4:$E$53,3,FALSE) -> 14852 | AG9: =AF9/$AF$18 -> #N/A | AJ9: Fancy Nahar Current Account | AK9: =VLOOKUP(AJ9,'Networth Inputs - old'!$C$4:$E$53,3,FALSE) -> #N/A | AL9: =AK9/$AK$26 -> #N/A
AE10: Zerodha Broking Mishayan: EQ Holdings | AF10: =VLOOKUP(AE10,'Networth Inputs - old'!$C$4:$E$53,3,FALSE) -> 24489026 | AG10: =AF10/$AF$18 -> #N/A | AJ10: Deepak Nahar Current Account - Qode | AK10: =VLOOKUP(AJ10,'Networth Inputs - old'!$C$4:$E$53,3,FALSE) -> #N/A | AL10: =AK10/$AK$26 -> #N/A
Z11: Total | AA11: =SUM(AA7:AA9) -> #N/A | AB11: =AA11/AA11 -> #N/A | AE11: Zerodha Broking Mishayan: EQ Mutual Fund | AF11: =VLOOKUP(AE11,'Networth Inputs - old'!$C$4:$E$53,3,FALSE) -> 2.9994569e+08 | AG11: =AF11/$AF$18 -> #N/A | AJ11: Aurus Alpha Deposit | AK11: =VLOOKUP(AJ11,'Networth Inputs - old'!$C$4:$E$53,3,FALSE) -> 31500000 | AL11: =AK11/$AK$26 -> #N/A
AE12: Sushila Nahar Equity MF | AF12: =VLOOKUP(AE12,'Networth Inputs - old'!$C$4:$E$53,3,FALSE) -> 15368350 | AG12: =AF12/$AF$18 -> #N/A | AJ12: Aurus Alpha FD Deposit | AK12: =VLOOKUP(AJ12,'Networth Inputs - old'!$C$4:$E$53,3,FALSE) -> #N/A | AL12: =AK12/$AK$26 -> #N/A
Z13: Leverage on Networth | AB13: =AA11/B5 -> #N/A | AE13: Yogita Agrawal QGF | AF13: =VLOOKUP(AE13,'Networth Inputs - old'!$C$4:$E$53,3,FALSE) -> #N/A | AG13: =AF13/$AF$18 -> #N/A | AJ13: Swan Capital | AK13: =VLOOKUP(AJ13,'Networth Inputs - old'!$C$4:$E$53,3,FALSE) -> 5881036 | AL13: =AK13/$AK$26 -> #N/A
Z14: Leverage on Liquidity | AB14: =AA11/B3 -> #N/A | AE14: PMS QFH Strategy | AF14: =VLOOKUP(AE14,'Networth Inputs - old'!$C$4:$E$53,3,FALSE) -> 6092676 | AG14: =AF14/$AF$18 -> #N/A | AJ14: HDFC Bank RN | AK14: =VLOOKUP(AJ14,'Networth Inputs - old'!$C$4:$E$53,3,FALSE) -> 1550293 | AL14: =AK14/$AK$26 -> #N/A
AJ15: HDFC Bank Mishayan | AK15: =VLOOKUP(AJ15,'Networth Inputs - old'!$C$4:$E$53,3,FALSE) -> 4287189 | AL15: =AK15/$AK$26 -> #N/A
AJ16: YG | AK16: =VLOOKUP(AJ16,'Networth Inputs - old'!$C$4:$E$53,3,FALSE) -> #N/A | AL16: =AK16/$AK$26 -> #N/A
AJ17: Interest Hand | AK17: =VLOOKUP(AJ17,'Networth Inputs - old'!$C$4:$E$53,3,FALSE) -> 0 | AL17: =AK17/$AK$26 -> #N/A
AE18: Total | AF18: =SUM(AF7:AF16) -> #N/A | AG18: =AF18/$AF$18 -> #N/A | AJ18: FD | AK18: =VLOOKUP(AJ18,'Networth Inputs - old'!$C$4:$E$53,3,FALSE) -> 23500000 | AL18: =AK18/$AK$26 -> #N/A
AJ19: Zerodha Broking Mishayan: Debt Mutual Fund | AK19: =VLOOKUP(AJ19,'Networth Inputs - old'!$C$4:$E$53,3,FALSE) -> 0 | AL19: =AK19/$AK$26 -> #N/A
AJ20: Zerodha Broking Mishayan: Liquidbees/ Liquidcase | AK20: =VLOOKUP(AJ20,'Networth Inputs - old'!$C$4:$E$53,3,FALSE) -> 0 | AL20: =AK20/$AK$26 -> #N/A
AE21: separate eq matrix because once we take other future exposure eg defence, it will be added here | AJ21: Zerodha Broking Mishayan: Cash | AK21: =VLOOKUP(AJ21,'Networth Inputs - old'!$C$4:$E$53,3,FALSE) -> 151543569 | AL21: =AK21/$AK$26 -> #N/A
AJ22: Gold India | AK22: =AA9 -> 166384100 | AL22: =AK22/$AK$26 -> #N/A
AJ26: Total | AK26: =SUM(AK7:AK24) -> #N/A | AL26: =AK26/$AK$26 -> #N/A
K30: Return Expectation | Q30: Risky Bets
T31: Other than this we have large cap mutual funds
Q32: Discretionary Stock | R32: =VLOOKUP(Q32,$F$27:$G$29,2,FALSE) -> #N/A | T32: worth 2 cr
K33: Particulars | L33: Exposure Values | M33: Expected Returns | N33: Profits | O33: % of total profit | Q33: % of Networth | R33: =R32/B5 -> #N/A
K34: Debt | L34: =GETPIVOTDATA("Total Value",Mastersheet!$AN$9,"Equity / Debt","Debt") -> 4.4792142e+08 | M34: 0.05 | N34: =M34*L34 -> 22396071 | O34: =N34/$N$45 -> #REF! | Q34: % of Liquidity | R34: =R32/B3 -> #N/A
K35: Equity | L35: =GETPIVOTDATA("Total Value",Mastersheet!$AN$9,"Equity / Debt","Equity") -> 3.204756e+08 | M35: 0.12 | N35: =M35*L35 -> 38457072 | O35: =N35/$N$45 -> #REF!
K36: =K4 -> 0 | L36: =GETPIVOTDATA("Total Exposure",$K$3,"Strategy Name","Gold") -> #REF! | M36: 0.06 | N36: =M36*L36 -> #REF! | O36: =N36/$N$45 -> #REF! | Q36: This should not be greater than 10%
K37: =K5 -> 0 | L37: =GETPIVOTDATA("Total Exposure",$K$3,"Strategy Name","Long Options") -> #REF! | M37: 0.04 | N37: =M37*L37 -> #REF! | O37: =N37/$N$45 -> #REF!
K38: =K6 -> 0 | L38: =GETPIVOTDATA("Total Exposure",$K$3,"Strategy Name","PSAR") -> #REF! | M38: 0.06 | N38: =M38*L38 -> #REF! | O38: =N38/$N$45 -> #REF!
K39: =K7 -> 0 | L39: =GETPIVOTDATA("Total Exposure",$K$3,"Strategy Name","Put Protection") -> #REF! | M39: -0.02 | N39: =M39*L39 -> #REF! | O39: =N39/$N$45 -> #REF! | Q39: PMS | T39: QAW
Q41: QMF | R41: =VLOOKUP(Q41,$F$27:$G$29,2,FALSE) -> #N/A | T41: QAW | U41: =VLOOKUP(T41,$F$27:$G$29,2,FALSE) -> #N/A | V41: =U41/$U$47 -> #N/A
K42: Less: Interest | L42: =B4 -> 67500000 | M42: -0.09 | N42: =M42*L42 -> -6075000 | O42: =N42/$N$45 -> #REF! | Q42: PMS QFH Strategy | R42: =VLOOKUP(Q42,$F$27:$G$29,2,FALSE) -> #N/A | T42: Momentum | U42: =VLOOKUP(T42,$F$27:$G$29,2,FALSE) -> #N/A | V42: =U42/$U$47 -> #N/A
Q43: Sushila Nahar Equity MF | R43: =VLOOKUP(Q43,$F$27:$G$29,2,FALSE) -> #N/A | T43: Low Vol | U43: =VLOOKUP(T43,$F$27:$G$29,2,FALSE) -> #N/A | V43: =U43/$U$47 -> #N/A
Q44: Yogita Agrawal PMS | R44: =VLOOKUP(Q44,$F$27:$G$29,2,FALSE) -> #N/A | T44: QAW Futures | U44: =VLOOKUP(T44,$K$4:$L$22,2,FALSE) -> #N/A | V44: =U44/$U$47 -> #N/A
K45: Total | N45: =SUM(N34:N42) -> #REF! | Q45: Total | R45: =SUM(R41:R44) -> #N/A | T45: Gold Futures | U45: =VLOOKUP(T45,$K$4:$L$22,2,FALSE) -> #N/A | V45: =U45/$U$47 -> #N/A
K46: % of Networth | N46: =N45/B5 -> #REF! | T46: Gold | U46: =VLOOKUP(T46,$K$4:$L$22,2,FALSE) -> #N/A | V46: =U46/$U$47 -> #N/A
K47: % of Liquidity | N47: =N45/B3 -> #REF! | Q47: % of Networth | R47: =R45/B5 -> #N/A | T47: Total | U47: =SUM(U41:U46) -> #N/A
Q48: % of Liquidity | R48: =R45/B3 -> #N/A
T49: % of Networth | U49: =U47/B5 -> #N/A
Q50: This should not be more than 25% | T50: % of Liquidity | U50: =U47/B3 -> #N/A
T52: QAW++ to run on 2x of the book

Sheet Mastersheet
D2: Networth | E2: =E3-E4 -> 8.3137254e+08
D3: Liquidity | E3: ='Networth Inputs - old'!Q4 -> 8.9887254e+08 | F3: =E3/$E$2 -> 1.081191
D4: Debt | E4: ='Networth Inputs - old'!Q5 -> 67500000 | F4: =E4/$E$2 -> 0.081191038
AE7: FnO Strategies | AN7: Underlying Book | AY7: Other Ratios | BH7: Return Expectation
B8: Liquidity | L8: Investment Summary | V8: Value At Risk
AN9: Equity / Debt / Gold / Cash | AO9: Total Value | AP9: % | AY9: Risky Bets | BC9: QAW | BH9: Particulars | BI9: Exposure Values | BJ9: Expected Returns | BK9: Profits | BL9: % of total profit
B10: Rishabh Nahar | C10: =SUMIFS('Networth Inputs - old'!$E$4:$E$77,'Networth Inputs - old'!$F$4:$F$77,Mastersheet!$B$10) -> 3.8610707e+08 | D10: =C10/$E$3 -> 0.42954596 | F10: Mishayan | G10: =SUMIFS('Networth Inputs - old'!$E$4:$E$77,'Networth Inputs - old'!$F$4:$F$77,Mastersheet!$F$10) -> 5.1276547e+08 | H10: =G10/$E$3 -> 0.57045404 | N10: Total Investments | O10: =M19+Q19 -> 1.1055895e+09 | V10: Strategy | W10: % Loss | X10: Loss Value | AN10: Cash | AO10: 1.9114102e+08 | AP10: 0.1979298 | BH10: Debt | BI10: =AT36+AT37 -> 49426199 | BJ10: 0.05 | BK10: =BJ10*BI10 -> 2471310 | BL10: =BK10/$BK$17 -> 0.0069987565
N11: Leverage on Networth | O11: =O10/E2 -> 1.3298364 | V11: Long Options | W11: -1 | X11: =W11*W27 -> -24471886 | AE11: Particulars | AF11: Sum of Net Exposure | AG11: % | AI11: % of Networth | AJ11: % of Liquidity | AN11: Debt | AO11: 4.4792142e+08 | AP11: 0.46383029 | AY11: Discretionary Stock | AZ11: =VLOOKUP(AY11,$AN$22:$AO$35,2,FALSE)+VLOOKUP("Sumesh",$AN$22:$AO$35,2,FALSE) -> 47098491 | BC11: QAW | BD11: =VLOOKUP(BC11,$P$33:$R$48,2,FALSE) -> 0 | BH11: Equity | BI11: =N15 -> 5.4595181e+08 | BJ11: 0.15 | BK11: =BJ11*BI11 -> 81892771 | BL11: =BK11/$BK$17 -> 0.23192055
B12: {=IFERROR(INDEX('Networth Inputs - old'!$B$4:$B$75, MATCH(0, COUNTIF($B$12:B12, 'Networth Inputs - old'!$B$4:$B$75), 0)), "")} -> 0 | C12: =SUMIFS('Networth Inputs - old'!$E$4:$E$77,'Networth Inputs - old'!$F$4:$F$77,Mastersheet!$B$10,'Networth Inputs - old'!$B$4:$B$77,Mastersheet!B12) -> 0 | D12: =C12/$C$10 -> 0 | F12: {=IFERROR(INDEX('Networth Inputs - old'!$B$4:$B$75, MATCH(0, COUNTIF($F$12:F12, 'Networth Inputs - old'!$B$4:$B$75), 0)), "")} -> 0 | G12: =SUMIFS('Networth Inputs - old'!$E$4:$E$77,'Networth Inputs - old'!$F$4:$F$77,Mastersheet!$F$10,'Networth Inputs - old'!$B$4:$B$77,Mastersheet!F12) -> 0 | H12: =G12/$G$10 -> 0 | N12: Leverage on Liquidity | O12: =O10/E3 -> 1.2299736 | V12: PSAR | W12: -0.1 | X12: =-AA50+W12*Y45 -> -2.3954187e+08 | AE12: Gold | AF12: 304237500 | AG12: 0.042986273 | AI12: =AF12/$E$2 -> 0.36594605 | AJ12: =AF12/$E$3 -> 0.33846567 | AN12: Equity | AO12: 3.204756e+08 | AP12: 0.33185796 | AY12: % of Networth | AZ12: =AZ11/$E$2 -> 0.056651487 | BC12: Momentum | BD12: =VLOOKUP(BC12,$L$33:$N$48,2,FALSE) -> 10931181 | BH12: Gold | BI12: =N16 -> 559637687 | BJ12: 0.06 | BK12: =BJ12*BI12 -> 33578261 | BL12: =BK12/$BK$17 -> 0.095093727
B13: {=IFERROR(INDEX('Networth Inputs - old'!$B$4:$B$75, MATCH(0, COUNTIF($B$12:B13, 'Networth Inputs - old'!$B$4:$B$75), 0)), "")} -> Other Investments | C13: =SUMIFS('Networth Inputs - old'!$E$4:$E$77,'Networth Inputs - old'!$F$4:$F$77,Mastersheet!$B$10,'Networth Inputs - old'!$B$4:$B$77,Mastersheet!B13) -> 1.1484056e+08 | D13: =C13/$C$10 -> 0.2974319 | F13: {=IFERROR(INDEX('Networth Inputs - old'!$B$4:$B$75, MATCH(0, COUNTIF($F$12:F13, 'Networth Inputs - old'!$B$4:$B$75), 0)), "")} -> Other Investments | G13: =SUMIFS('Networth Inputs - old'!$E$4:$E$77,'Networth Inputs - old'!$F$4:$F$77,Mastersheet!$F$10,'Networth Inputs - old'!$B$4:$B$77,Mastersheet!F13) -> 0 | H13: =G13/$G$10 -> 0 | V13: Put Protection | W13: 0.05 | X13: =W13*M19 -> 27297590 | AE13: Gold Futures | AF13: 255400187 | AG13: 0.03608596 | AI13: =AF13/$E$2 -> 0.30720306 | AJ13: =AF13/$E$3 -> 0.28413393 | AN13: Gold | AO13: 6163056 | AP13: 0.0063819499 | AY13: % of Liquidity | AZ13: =AZ11/$E$3 -> 0.052397296 | BC13: Low Vol | BD13: =VLOOKUP(BC13,$L$33:$N$48,2,FALSE) -> 0 | BH13: Long Options | BI13: =AF15 -> 3.8923671e+09 | BJ13: 0.05 | BK13: =BJ13*BI13 -> 1.9461836e+08 | BL13: =BK13/$BK$17 -> 0.55115971
B14: {=IFERROR(INDEX('Networth Inputs - old'!$B$4:$B$75, MATCH(0, COUNTIF($B$12:B14, 'Networth Inputs - old'!$B$4:$B$75), 0)), "")} -> FD | C14: =SUMIFS('Networth Inputs - old'!$E$4:$E$77,'Networth Inputs - old'!$F$4:$F$77,Mastersheet!$B$10,'Networth Inputs - old'!$B$4:$B$77,Mastersheet!B14) -> 76648751 | D14: =C14/$C$10 -> 0.19851683 | F14: {=IFERROR(INDEX('Networth Inputs - old'!$B$4:$B$75, MATCH(0, COUNTIF($F$12:F14, 'Networth Inputs - old'!$B$4:$B$75), 0)), "")} -> FD | G14: =SUMIFS('Networth Inputs - old'!$E$4:$E$77,'Networth Inputs - old'!$F$4:$F$77,Mastersheet!$F$10,'Networth Inputs - old'!$B$4:$B$77,Mastersheet!F14) -> 5287189 | H14: =G14/$G$10 -> 0.010311125 | M14: Investment | N14: Amount | O14: % of Total Investments | P14: Leverage on Networth | Q14: Leverage on Liquidity | V14: Equities | W14: -0.2 | X14: =W14*N15 -> -1.0919036e+08 | AE14: Long Options | AF14: 1.5123121e+09 | AG14: 0.21367734 | AI14: =AF14/$E$2 -> 1.8190546 | AJ14: =AF14/$E$3 -> 1.6824544 | AN14: Grand Total | AO14: 9.657011e+08 | AP14: 1 | BC14: QAW Futures | BD14: =VLOOKUP(BC14,$L$33:$N$48,2,FALSE) -> 4.0546308e+08 | BH14: PSAR | BI14: =AF17 -> 4.0546308e+08 | BJ14: 0.1 | BK14: =BJ14*BI14 -> 40546308 | BL14: =BK14/$BK$17 -> 0.11482725
B15: {=IFERROR(INDEX('Networth Inputs - old'!$B$4:$B$75, MATCH(0, COUNTIF($B$12:B15, 'Networth Inputs - old'!$B$4:$B$75), 0)), "")} -> Prop Deposits | C15: =SUMIFS('Networth Inputs - old'!$E$4:$E$77,'Networth Inputs - old'!$F$4:$F$77,Mastersheet!$B$10,'Networth Inputs - old'!$B$4:$B$77,Mastersheet!B15) -> 1.0807881e+08 | D15: =C15/$C$10 -> 0.27991926 | F15: {=IFERROR(INDEX('Networth Inputs - old'!$B$4:$B$75, MATCH(0, COUNTIF($F$12:F15, 'Networth Inputs - old'!$B$4:$B$75), 0)), "")} -> Prop Deposits | G15: =SUMIFS('Networth Inputs - old'!$E$4:$E$77,'Networth Inputs - old'!$F$4:$F$77,Mastersheet!$F$10,'Networth Inputs - old'!$B$4:$B$77,Mastersheet!F15) -> 31500000 | H15: =G15/$G$10 -> 0.061431593 | M15: Equity | N15: =M19 -> 5.4595181e+08 | O15: =N15/$O$10 -> 0.4938106 | P15: =N15/E2 -> 0.65668732 | Q15: =N15/E3 -> 0.60737399 | V15: Gold | W15: 0.05 | X15: =W15*N16 -> 27981884 | AE15: PSAR | AF15: 3.8923671e+09 | AG15: 0.54995967 | AI15: =AF15/$E$2 -> 4.6818567 | AJ15: =AF15/$E$3 -> 4.330277 | AY15: This should not be greater than 10% | BC15: Gold Futures | BD15: =VLOOKUP(BC15,$P$33:$R$48,2,FALSE) -> 255400187
B16: {=IFERROR(INDEX('Networth Inputs - old'!$B$4:$B$75, MATCH(0, COUNTIF($B$12:B16, 'Networth Inputs - old'!$B$4:$B$75), 0)), "")} | C16: =SUMIFS('Networth Inputs - old'!$E$4:$E$77,'Networth Inputs - old'!$F$4:$F$77,Mastersheet!$B$10,'Networth Inputs - old'!$B$4:$B$77,Mastersheet!B16) -> 0 | D16: =C16/$C$10 -> 0 | F16: {=IFERROR(INDEX('Networth Inputs - old'!$B$4:$B$75, MATCH(0, COUNTIF($F$12:F16, 'Networth Inputs - old'!$B$4:$B$75), 0)), "")} | G16: =SUMIFS('Networth Inputs - old'!$E$4:$E$77,'Networth Inputs - old'!$F$4:$F$77,Mastersheet!$F$10,'Networth Inputs - old'!$B$4:$B$77,Mastersheet!F16) -> 0 | H16: =G16/$G$10 -> 0 | M16: Gold | N16: =Q34+Q35 -> 559637687 | O16: =N16/$O$10 -> 0.5061894 | P16: =N16/E2 -> 0.67314911 | Q16: =N16/E3 -> 0.6225996 | AE16: Put Protection | AF16: 6.6631014e+08 | AG16: 0.094144179 | AI16: =AF16/$E$2 -> 0.80145796 | AJ16: =AF16/$E$3 -> 0.74127322 | BC16: Gold | BD16: =VLOOKUP(BC16,$P$33:$R$48,2,FALSE) -> 304237500
B17: {=IFERROR(INDEX('Networth Inputs - old'!$B$4:$B$75, MATCH(0, COUNTIF($B$12:B17, 'Networth Inputs - old'!$B$4:$B$75), 0)), "")} -> Client Account | C17: =SUMIFS('Networth Inputs - old'!$E$4:$E$77,'Networth Inputs - old'!$F$4:$F$77,Mastersheet!$B$10,'Networth Inputs - old'!$B$4:$B$77,Mastersheet!B17) -> 86538956 | D17: =C17/$C$10 -> 0.22413201 | F17: {=IFERROR(INDEX('Networth Inputs - old'!$B$4:$B$75, MATCH(0, COUNTIF($F$12:F17, 'Networth Inputs - old'!$B$4:$B$75), 0)), "")} -> Client Account | G17: =SUMIFS('Networth Inputs - old'!$E$4:$E$77,'Networth Inputs - old'!$F$4:$F$77,Mastersheet!$F$10,'Networth Inputs - old'!$B$4:$B$77,Mastersheet!F17) -> 4.7597828e+08 | H17: =G17/$G$10 -> 0.92825728 | AE17: QAW Futures | AF17: 4.0546308e+08 | AG17: 0.05728862 | AI17: =AF17/$E$2 -> 0.48770324 | AJ17: =AF17/$E$3 -> 0.45107961 | AN17: Equity Categorisation | AS17: Debt Categorisation | BC17: Total | BD17: =SUM(BD11:BD16) -> 9.7603195e+08 | BH17: Total | BI17: =SUM(BI10:BI14) -> 5.4528459e+09 | BJ17: =BK17/BI17 -> 0.064756462 | BK17: =SUM(BK10:BK14) -> 3.5310701e+08
V18: Total Loss | X18: =SUM(X11:X16) -> -3.1792464e+08 | AE18: Stock Futures | AF18: 41460000 | AG18: 0.0058579592 | AI18: =AF18/$E$2 -> 0.04986934 | AJ18: =AF18/$E$3 -> 0.046124448 | AY18: PMS
L19: Equity / Aggressive | M19: =L24+N24 -> 5.4595181e+08 | N19: =M19/O10 -> 0.4938106 | P19: Inflation Hedge / Defensive | Q19: =P24+R24 -> 559637687 | R19: =Q19/O10 -> 0.5061894 | V19: Loss on Networth | X19: =X18/E2 -> -0.38240936 | AE19: (blank) | AG19: 0 | AI19: =AF19/$E$2 -> 0 | AJ19: =AF19/$E$3 -> 0 | AN19: Column | AO19: Value as of Today | AS19: Equity / Debt | AT19: Debt | BC19: % of Networth | BD19: =BD17/E2 -> 1.1740007
L20: Leverage on Networth | N20: =M19/E2 -> 0.65668732 | P20: Leverage on Networth | R20: =Q19/E2 -> 0.67314911 | V20: Loss on Liquidity | X20: =X18/E3 -> -0.35369268 | AE20: Gold PRCS | AF20: 0 | AG20: 0 | AI20: =AF20/$E$2 -> 0 | AJ20: =AF20/$E$3 -> 0 | AY20: QMF | AZ20: =VLOOKUP(AY20,$AN$21:$AO$35,2,FALSE) -> 47052658 | BC20: % of Liquidity | BD20: =BD17/E3 -> 1.0858402
B21: Account | C21: Rishabh Nahar | F21: Account | G21: Mishayan | L21: Leverage on Liquidity | N21: =M19/E3 -> 0.60737399 | P21: Leverage on Liquidity | R21: =Q19/E3 -> 0.6225996 | AE21: Grand Total | AF21: 7.0775501e+09 | AG21: 1 | AI21: =AF21/$E$2 -> 8.513091 | AJ21: =AF21/$E$3 -> 7.8738083 | AN21: Particulars | AO21: Total Value | AP21: % | AS21: Row Labels | AT21: Total Value | AU21: % | AY21: PMS QFH Strategy | AZ21: =VLOOKUP(AY21,$AN$21:$AO$35,2,FALSE) -> 6092676
AI22: =AF22/$E$2 -> 0 | AJ22: =AF22/$E$3 -> 0 | AN22: Large Cap | AO22: 18310601 | AP22: 0.056057667 | AS22: Affluence | AT22: 5591229.8 | AU22: 0.012482613 | AY22: Sushila Nahar Equity MF | AZ22: =VLOOKUP(AY22,$AN$21:$AO$35,2,FALSE) -> 15368350 | BC22: QAW++ to run on 2x of the book
B23: Particulars | C23: Total Value | D23: % | F23: Particulars | G23: Total Value | H23: % | L23: India | N23: Global | P23: India | R23: Global | AI23: =AF23/$E$2 -> 0 | AJ23: =AF23/$E$3 -> 0 | AN23: Momentum | AO23: 1.0285723e+08 | AP23: 0.31489607 | AS23: Aurus Alpha Deposit | AT23: 31500000 | AU23: 0.070324835 | AY23: Yogita Agrawal PMS | AZ23: =VLOOKUP(AY23,$AN$21:$AO$35,2,FALSE) -> 40685877
B24: Client Account | C24: 1.1140911e+08 | D24: 0.2629092 | F24: Client Account | G24: 5.0515882e+08 | H24: 0.9321202 | L24: =M33 -> 5.4595181e+08 | N24: =M49 -> 0 | P24: =Q33 -> 559637687 | R24: =Q49 -> 0 | AI24: =AF24/$E$2 -> 0 | AJ24: =AF24/$E$3 -> 0 | AN24: PMS QFH Strategy | AO24: 6092676 | AP24: 0.018652649 | AS24: FD | AT24: 23500000 | AU24: 0.052464559 | AY24: Total | AZ24: =SUM(AZ20:AZ23) -> 1.0919956e+08
B25: Zerodha Broking RN: Cash | C25: 14852 | D25: 3.5048547e-05 | F25: Zerodha Broking Mishayan: Cash | G25: 1.8528869e+08 | H25: 0.3418951 | L25: =L24/M19 -> 1 | N25: =N24/M19 -> 0 | P25: =P24/Q19 -> 1 | R25: =R24/Q19 -> 0 | V25: Long Options and Psar | AN25: Sushila Nahar Equity MF | AO25: 15368350 | AP25: 0.047050004 | AS25: Interest Hand | AT25: 0 | AU25: 0
B26: Zerodha Broking RN: Debt Mutual Funds | C26: 3946196.5 | D26: 0.0093124464 | F26: Zerodha Broking Mishayan: Debt Mutual Fund | G26: 1.5623862e+08 | H26: 0.28829185 | AN26: Low Vol | AO26: 29509719 | AP26: 0.09034362 | AS26: Loan to Vihaan | AT26: 3000000 | AU26: 0.0066976033 | AY26: % of Networth | AZ26: =AZ24/$E$2 -> 0.13134853 | BC26: gold | BD26: =BD16+BD15 -> 559637687
B27: Zerodha Broking RN: EQ Holdings | C27: 1.0744806e+08 | D27: 0.2535617 | F27: Zerodha Broking Mishayan: EQ Holdings | G27: 4298337.5 | H27: 0.007931302 | V27: Long Options Total Premium | W27: =SUMIFS('Strategy Allocation Old'!$G$5:$G$97,'Strategy Allocation Old'!$C$5:$C$97,"Long Options") -> 24471886 | AN27: QMF | AO27: 47052658 | AP27: 0.1440511 | AS27: Swan Capital | AT27: 5881036 | AU27: 0.013129615 | AY27: % of Liquidity | AZ27: =AZ24/$E$3 -> 0.12148503 | BC27: low vol | BD27: =BD13 -> 0
B28: Zerodha Broking RN: EQ Mutual Funds | C28: 0 | D28: 0 | F28: Zerodha Broking Mishayan: EQ Mutual Fund | G28: 1.3924535e+08 | H28: 0.25693584 | V28: % of Networth | W28: =W27/E2 -> 0.029435523 | AN28: Discretionary Stock | AO28: 27268789 | AP28: 0.083483044 | AS28: YG | AT28: 30312620 | AU28: 0.067673967 | BC28: mom | BD28: =BD12 -> 10931181
B29: FD | C29: 76648751 | D29: 0.18087984 | F29: Zerodha Broking Mishayan: Liquidbees/ Liquidcase | G29: 20087829 | H29: 0.037066108 | V29: % of Liquidity | W29: =W27/E3 -> 0.02722509 | AN29: QAW | AO29: 6163056 | AP29: 0.018868116 | AS29: Zerodha Broking Mishayan: Debt Mutual Fund | AT29: 1.5623862e+08 | AU29: 0.34880809 | AY29: This should not be more than 25%
B30: FD | C30: 23500000 | D30: 0.055456562 | F30: FD | G30: 5287189 | H30: 0.009755933 | AN30: Yogita Agrawal PMS | AO30: 40685877 | AP30: 0.12455928 | AS30: Zerodha Broking Mishayan: Liquidbees/ Liquidcase | AT30: 20087829 | AU30: 0.044846771
B31: HDFC Bank RN | C31: 1550293 | D31: 0.0036584647 | F31: HDFC Bank Mishayan | G31: 4287189 | H31: 0.0079107308 | V31: Psar Total Exposure | W31: =SUMIFS('Strategy Allocation Old'!$F$5:$F$97,'Strategy Allocation Old'!$C$5:$C$97,"PSAR") -> 3.7777797e+09 | AN31: Sumesh | AO31: 19829702 | AP31: 0.060708374 | AS31: Zerodha Broking RN: Debt Mutual Funds | AT31: 3946196.5 | AU31: 0.0088100196
B32: ICICI Bank OD | C32: 48398458 | D32: 0.11421328 | F32: HDFC Bank FD | G32: 1000000 | H32: 0.0018452022 | V32: Leverage on Networth | W32: =W31/E2 -> 4.5440274 | AE32: Strategy | AF32: Sum of Net Exposure | AN32: Sushila Nahar Zerodha | AO32: 13500000 | AP32: 0.041330075 | AS32: Affluence High Risk | AT32: 5128618.5 | AU32: 0.011449817 | AY32: Other than this we have large cap mutual funds
B33: Nimai FD | C33: 0 | D33: 0 | F33: Prop Deposits | G33: 31500000 | H33: 0.058123871 | L33: India | M33: =SUM(M34:M45) -> 5.4595181e+08 | N33: =M33/M19 -> 1 | P33: India | Q33: =SUM(Q34:Q36) -> 559637687 | R33: =Q33/Q19 -> 1 | V33: Leverage on Liquidity | W33: =W31/E3 -> 4.2027979 | AE33: Gold | AF33: 304237500 | AN33: Grand Total | AO33: 3.2663865e+08 | AP33: 1 | AS33: ICICI Bank OD | AT33: 48398458 | AU33: 0.10805122 | AY33: worth 2 cr
B34: Arvind FD | C34: 700000 | D34: 0.0016518976 | F34: Aurus Alpha Deposit | G34: 31500000 | H34: 0.058123871 | P34: Gold Futures | Q34: =SUMIFS('Strategy Allocation Old'!$F$5:$F$64,'Strategy Allocation Old'!$C$5:$C$64,Mastersheet!P34) -> 255400187 | R34: =Q34/$Q$33 -> 0.45636703 | AE34: Mishayan Zerodha Client Account | AF34: 304237500 | AS34: Jainam Allocation Deposit | AT34: 0 | AU34: 0
B35: Sumesh FD | C35: 2500000 | D35: 0.0058996342 | F35: Grand Total | G35: 5.4194601e+08 | H35: 1 | L35: QMF | M35: =SUMIFS('Mutual Funds'!$L$24:$L$79,'Mutual Funds'!$H$24:$H$79,L35)+SUMIFS('Equity Holdings'!$K$4:$K$83,'Equity Holdings'!$H$4:$H$83,L35) -> 44949446 | N35: =M35/$M$33 -> 0.08233226 | P35: Gold | Q35: =SUMIFS('Strategy Allocation Old'!$F$5:$F$64,'Strategy Allocation Old'!$C$5:$C$64,Mastersheet!P35) -> 304237500 | R35: =Q35/$Q$33 -> 0.54363297 | AE35: Gold Futures | AF35: 255400187 | AS35: Aurus Alpha Profit | AT35: 42915812 | AU35: 0.095811028
B36: Other Investments | C36: 1.1484056e+08 | D36: 0.27100692 | L36: Discretionary Stock | M36: =SUMIFS('Mutual Funds'!$L$24:$L$79,'Mutual Funds'!$H$24:$H$79,L36)+SUMIFS('Equity Holdings'!$K$4:$K$83,'Equity Holdings'!$H$4:$H$83,L36) -> 25657302 | N36: =M36/$M$33 -> 0.046995544 | P36: QAW | Q36: =SUMIFS('Mutual Funds'!$L$24:$L$79,'Mutual Funds'!$H$24:$H$79,P36)+SUMIFS('Equity Holdings'!$K$4:$K$83,'Equity Holdings'!$H$4:$H$83,P36) -> 0 | R36: =Q36/$Q$33 -> 0 | AE36: Affluence Prop | AF36: 10449600 | AS36: Marwadi Deposit | AT36: 10200000 | AU36: 0.022771851
B37: Interest Hand | C37: 0 | D37: 0 | L37: Momentum | M37: =SUMIFS('Mutual Funds'!$L$24:$L$79,'Mutual Funds'!$H$24:$H$79,L37)+SUMIFS('Equity Holdings'!$K$4:$K$83,'Equity Holdings'!$H$4:$H$83,L37) -> 10931181 | N37: =M37/$M$33 -> 0.020022246 | V37: PSAR Portfolio Values | AE37: Aurus Alpha | AF37: 116732187 | AN37: Cash Categorisation | AS37: Marwadi Profits | AT37: 39226199 | AU37: 0.08757384
B38: Loan to Vihaan | C38: 3000000 | D38: 0.0070795611 | L38: Low Vol | M38: =SUMIFS('Mutual Funds'!$L$24:$L$79,'Mutual Funds'!$H$24:$H$79,L38)+SUMIFS('Equity Holdings'!$K$4:$K$83,'Equity Holdings'!$H$4:$H$83,L38) -> 0 | N38: =M38/$M$33 -> 0 | AE38: SRE | AF38: 0 | AS38: Marwadi FPI Deposit (FD) | AT38: 2625000 | AU38: 0.0058604029
B39: PMS QFH Strategy | C39: 6092676 | D39: 0.014377824 | L39: Large Cap | M39: =SUMIFS('Mutual Funds'!$L$24:$L$79,'Mutual Funds'!$H$24:$H$79,L39)+SUMIFS('Equity Holdings'!$K$4:$K$83,'Equity Holdings'!$H$4:$H$83,L39) -> 0 | N39: =M39/$M$33 -> 0 | V39: Strategy Name | W39: PSAR | AE39: Marwadi | AF39: 90922400 | AN39: Equity / Debt | AO39: Cash | AS39: HDFC Bank FD | AT39: 1000000 | AU39: 0.0022325344
B40: Sushila Nahar Equity MF | C40: 15368350 | D40: 0.036267057 | L40: Sushila Nahar Equity MF | M40: =SUMIFS('Mutual Funds'!$L$24:$L$79,'Mutual Funds'!$H$24:$H$79,L40)+SUMIFS('Equity Holdings'!$K$4:$K$83,'Equity Holdings'!$H$4:$H$83,L40) -> 0 | N40: =M40/$M$33 -> 0 | AE40: Marwadi FPI | AF40: 37296000 | AS40: Marwadi FPI Profits | AT40: 15169806 | AU40: 0.033867114
B41: Swan Capital | C41: 5881036 | D41: 0.013878384 | L41: Yogita Agrawal PMS | M41: =SUMIFS('Mutual Funds'!$L$24:$L$79,'Mutual Funds'!$H$24:$H$79,L41)+SUMIFS('Equity Holdings'!$K$4:$K$83,'Equity Holdings'!$H$4:$H$83,L41) -> 0 | N41: =M41/$M$33 -> 0 | V41: Account | W41: Portfolio Value | X41: Psar Multiplier | Y41: Total Exposure | Z41: Hedge | AA41: VAR | AE41: Long Options | AF41: 1.5123121e+09 | AN41: Particulars | AO41: Total Value | AP41: % | AS41: Nimai FD | AT41: 0 | AU41: 0
B42: YG | C42: 30312620 | D42: 0.071533348 | L42: PMS QFH Strategy | M42: =SUMIFS('Mutual Funds'!$L$24:$L$79,'Mutual Funds'!$H$24:$H$79,L42)+SUMIFS('Equity Holdings'!$K$4:$K$83,'Equity Holdings'!$H$4:$H$83,L42) -> 0 | N42: =M42/$M$33 -> 0 | V42: Affluence High Risk | W42: 20737500 | X42: 6 | Y42: 124425000 | Z42: 0.1 | AA42: =IF(Z42>0%,W42*Z42,Z42*Y42) -> 2073750 | AE42: Affluence High Risk | AF42: 20737500 | AN42: HDFC Bank Mishayan | AO42: 4287189 | AP42: 0.022429455 | AS42: Arvind FD | AT42: 700000 | AU42: 0.0015627741
B43: Yogita Agrawal PMS | C43: 40685877 | D43: 0.096012717 | L43: Stock Futures | M43: =SUMIFS('Strategy Allocation Old'!$F$5:$F$64,'Strategy Allocation Old'!$C$5:$C$64,Mastersheet!L43) -> 41460000 | N43: =M43/$M$33 -> 0.075940769 | V43: Affluence Prop | W43: 26124000 | X43: 3 | Y43: 78372000 | Z43: 0.1 | AA43: =IF(Z43>0%,W43*Z43,Z43*Y43) -> 2612400 | AE43: Affluence Prop | AF43: 26124000 | AN43: HDFC Bank RN | AO43: 1550293 | AP43: 0.0081107289 | AS43: Sumesh FD | AT43: 2500000 | AU43: 0.0055813361
B44: Sushila Nahar HDFC | C44: 0 | D44: 0 | L44: QAW Futures | M44: =SUMIFS('Strategy Allocation Old'!$F$5:$F$64,'Strategy Allocation Old'!$C$5:$C$64,Mastersheet!L44) -> 4.0546308e+08 | N44: =M44/$M$33 -> 0.74267193 | V44: Aurus Alpha | W44: 249427750 | X44: 3.34 | Y44: 833088685 | Z44: 0.1 | AA44: =IF(Z44>0%,W44*Z44,Z44*Y44) -> 24942775 | AE44: Aurus Alpha | AF44: 249427750 | AN44: Zerodha Broking Mishayan: Cash | AO44: 1.8528869e+08 | AP44: 0.96938211 | AS44: Grand Total | AT44: 4.4792142e+08 | AU44: 1
B45: Sushila Nahar Zerodha | C45: 13500000 | D45: 0.031858025 | L45: Sumesh | M45: =SUMIFS('Mutual Funds'!$L$24:$L$79,'Mutual Funds'!$H$24:$H$79,L45)+SUMIFS('Equity Holdings'!$K$4:$K$83,'Equity Holdings'!$H$4:$H$83,L45) -> 17490796 | N45: =M45/$M$33 -> 0.032037253 | V45: Mishayan Zerodha Client Account | W45: 7.8233181e+08 | X45: 2.12 | Y45: 1.6585434e+09 | Z45: 0 | AA45: =IF(Z45>0%,W45*Z45,Z45*Y45) -> 0 | AE45: Mishayan Zerodha Client Account | AF45: 7.8233181e+08 | AN45: Zerodha Broking RN: Cash | AO45: 14852 | AP45: 7.7701793e-05
B46: Prop Deposits | C46: 1.2085667e+08 | D46: 0.28520405 | V46: SRE | W46: 116820000 | X46: 2 | Y46: 233640000 | Z46: 0.1 | AA46: =IF(Z46>0%,W46*Z46,Z46*Y46) -> 11682000 | AE46: SRE | AF46: 116820000 | AN46: Sushila Nahar HDFC | AO46: 0 | AP46: 0
B47: Affluence | C47: 5591229.8 | D47: 0.013194484 | V47: Marwadi | W47: 227306000 | X47: 3 | Y47: 681918000 | Z47: 0.1 | AA47: =IF(Z47>0%,W47*Z47,Z47*Y47) -> 22730600 | AE47: Marwadi | AF47: 227306000 | AN47: Grand Total | AO47: 1.9114102e+08 | AP47: 1
B48: Affluence High Risk | C48: 5128618.5 | D48: 0.012102789 | V48: Marwadi FPI | W48: 89460000 | X48: 3 | Y48: 268380000 | Z48: 0.1 | AA48: =IF(Z48>0%,W48*Z48,Z48*Y48) -> 8946000 | AE48: Marwadi FPI | AF48: 89460000
B49: Aurus Alpha Profit | C49: 42915812 | D49: 0.10127504 | L49: Global | M49: =SUM(M50:M51) -> 0 | N49: =M49/M19 -> 0 | P49: Global | Q49: =SUM(Q50:Q51) -> 0 | R49: =Q49/Q19 -> 0 | V49: Ashika | W49: 7000000 | X49: 2 | Y49: 14000000 | Z49: 0.1 | AA49: =IF(Z49>0%,W49*Z49,Z49*Y49) -> 700000 | AE49: Ashika | AF49: 105000
B50: Marwadi Deposit | C50: 10200000 | D50: 0.024070508 | N50: =M50/$M$49 -> #DIV/0! | R50: =Q50/$Q$49 -> #DIV/0! | V50: Grand Total | W50: 1.5192071e+09 | X50: 24.46 | Y50: 3.8923671e+09 | AA50: =SUM(AA42:AA49) -> 73687525 | AE50: PSAR | AF50: 3.8923671e+09
B51: Marwadi Profits | C51: 39226199 | D51: 0.09256809 | N51: =M51/$M$49 -> #DIV/0! | R51: =Q51/$Q$49 -> #DIV/0! | AE51: Affluence High Risk | AF51: 124425000
B52: Marwadi FPI Deposit (FD) | C52: 2625000 | D52: 0.0061946159 | AE52: Affluence Prop | AF52: 78372000
B53: Marwadi FPI Profits | C53: 15169806 | D53: 0.035798523 | AE53: Aurus Alpha | AF53: 833088685
B54: Grand Total | C54: 4.2375508e+08 | D54: 1 | AE54: Mishayan Zerodha Client Account | AF54: 1.6585434e+09
AE55: SRE | AF55: 233640000
AE56: Marwadi | AF56: 681918000
AE57: Marwadi FPI | AF57: 268380000
AE58: Ashika | AF58: 14000000
AE59: Put Protection | AF59: 6.6631014e+08
AE60: Affluence Prop | AF60: 18824400
AE61: Aurus Alpha | AF61: 149656650
AE62: Mishayan Zerodha Client Account | AF62: 2.4482869e+08
AE63: SRE | AF63: 70092000
AE64: Marwadi | AF64: 129232400
AE65: Marwadi FPI | AF65: 53676000
AE66: QAW Futures | AF66: 4.0546308e+08
... AE75: Marwadi | AF75: 38310000
AE76: (blank)
AE77: (blank)
AE78: Gold PRCS | AF78: 0
AE79: Aurus Alpha | AF79: 0
AE80: Mishayan Zerodha Client Account | AF80: 0
AE81: Marwadi | AF81: 0
AE82: Grand Total | AF82: 7.0775501e+09

Sheet Capital Account
A2: Mishayan Capital Account Number as per Accounts | I2: Note: | V2: Current Liquidity | Z2: Mishayan Actual Liquidity | AD2: Rishabh Actual Liquidity | AI2: Networth
I3: FnO Open Positions End of Year WILL BE SUBTRACTED FROM REVENUE HENCE NEGATIVE
A4: Year | B4: FY | C4: Revenue / Expense | D4: Category | E4: Amount | I4: FnO Open Positions Start of Year WILL BE ADDED FROM REVENUE HENCE POSITIVE | V4: Particulars | W4: Sum of Value | Z4: Particulars | AA4: Value | AD4: Particulars | AE4: Value | AF4: BS | AJ4: Mishayan | AK4: Rishabh | AL4: Total
A5: 1 | B5: 2023-24 | C5: Revenue | D5: Consultancy Fees | E5: 1700000 | V5: Mishayan | W5: 5.4194601e+08 | Z5: Total | AA5: =SUM(AA6:AA38) -> 3.5902084e+08 | AD5: Total | AE5: =SUM(AE6:AE38) -> 6.0668026e+08 | AI5: Liquidity | AJ5: =AA5 -> 3.5902084e+08 | AK5: =AE5 -> 6.0668026e+08 | AL5: =AJ5+AK5 -> 9.657011e+08
A6: 2 | B6: 2024-25 | C6: Revenue | D6: Equity and Non Equity Profits | E6: 31 | V6: Aurus Alpha Deposit | W6: 31500000 | Z6: =V6 -> Aurus Alpha Deposit | AA6: =W6 -> 31500000 | AD6: =V15 -> Affluence | AE6: =W15 -> 5591229.8 | AF6: Off | AI6: Less: Debt | AJ6: 35300000 | AK6: ='Networth Inputs - old'!M4+'Networth Inputs - old'!M5+'Networth Inputs - old'!M6-'Capital Account'!AJ6+'Networth Inputs - old'!M7 -> 32200000 | AL6: =AJ6+AK6 -> 67500000
A7: 2 | B7: 2024-25 | C7: Expense | D7: Equity and Non Equity Other Debits | E7: -9594.1988 | J7: Row Labels | K7: Sum of Amount | V7: HDFC Bank Mishayan | W7: 4287189 | Z7: =V7 -> HDFC Bank Mishayan | AA7: =W7 -> 4287189 | AD7: =V16 -> Affluence High Risk | AE7: =W16 -> 5128618.5 | AF7: Off | AI7: Networth | AJ7: =AJ5-AJ6 -> 3.2372084e+08 | AK7: =AK5-AK6 -> 5.7448026e+08 | AL7: =AJ7+AK7 -> 8.982011e+08
A8: 2 | B8: 2024-25 | C8: Revenue | D8: Mutual Fund Profits | E8: -48533.882 | J8: 2023-24 | K8: 1192790 | V8: Zerodha Broking Mishayan: Cash | W8: 1.8528869e+08 | Z8: =V8 -> Zerodha Broking Mishayan: Cash | AA8: =W8 -> 1.8528869e+08 | AD8: =V17 -> FD | AE8: =W17 -> 23500000 | AF8: Off
A9: 2 | B9: 2024-25 | C9: Revenue | D9: FnO Profits | E9: 17841191 | J9: Expense | K9: -63743 | V9: Zerodha Broking Mishayan: Debt Mutual Fund | W9: 1.5623862e+08 | Z9: =V9 -> Zerodha Broking Mishayan: Debt Mutual Fund | AA9: =W9 -> 1.5623862e+08 | AD9: =V18 -> HDFC Bank RN | AE9: =W18 -> 1550293
A10: 2 | B10: 2024-25 | C10: Expense | D10: Fno Charges | E10: -1252925.9 | J10: Audit/Professional Fees | K10: -63743 | V10: Zerodha Broking Mishayan: EQ Holdings | W10: 4298337.5 | Z10: =V10 -> Zerodha Broking Mishayan: EQ Holdings | AA10: =W10 -> 4298337.5 | AD10: =V19 -> ICICI Bank OD | AE10: =W19 -> 48398458
A11: 2 | B11: 2024-25 | C11: Revenue | D11: FnO Open Positions End of Year | E11: -15847722 | J11: Revenue | K11: 1700000 | V11: Zerodha Broking Mishayan: EQ Mutual Fund | W11: 1.3924535e+08 | Z11: =V11 -> Zerodha Broking Mishayan: EQ Mutual Fund | AA11: =W11 -> 1.3924535e+08 | AD11: =V20 -> Interest Hand | AE11: =W20 -> 0 | AF11: Off | AI11: Liquidity
A12: 2 | B12: 2024-25 | C12: Revenue | D12: FnO Open Positions Start of Year | E12: =0 -> 0 | J12: Consultancy Fees | K12: 1700000 | V12: Zerodha Broking Mishayan: Liquidbees/ Liquidcase | W12: 20087829 | Z12: =V12 -> Zerodha Broking Mishayan: Liquidbees/ Liquidcase | AA12: =W12 -> 20087829 | AD12: =V21 -> Loan to Vihaan | AE12: =W21 -> 3000000 | AF12: On
A13: 2 | B13: 2024-25 | C13: Revenue | D13: Equity Dividends | E13: 0 | J13: Taxes | K13: -443467 | V13: HDFC Bank FD | W13: 1000000 | Z13: =V13 -> HDFC Bank FD | AA13: =W13 -> 1000000 | AD13: =V22 -> PMS QFH Strategy | AE13: =W22 -> 6092676 | AF13: On | AJ13: Mishayan | AK13: Rishabh | AL13: Total
A14: 3 | B14: 2025-26 | C14: Expense | D14: Equity and Non Equity Other Debits | E14: -13550.635 | J14: Taxes | K14: -443467 | V14: Rishabh Nahar | W14: 4.2375508e+08 | AD14: =V23 -> Sushila Nahar Equity MF | AE14: =W23 -> 15368350 | AI14: On | AJ14: =AJ5 -> 3.5902084e+08 | AK14: =SUMIFS($AE$7:$AE$110,$AF$7:$AF$110,AI14) -> 4.6870231e+08 | AL14: =AJ14+AK14 -> 8.2772315e+08
A15: 3 | B15: 2025-26 | C15: Revenue | D15: FnO Profits | E15: 93867317 | J15: 2024-25 | K15: 8905814.4 | V15: Affluence | W15: 5591229.8 | AD15: =V24 -> Swan Capital | AE15: =W24 -> 5881036 | AF15: On | AI15: Off | AK15: =SUMIFS($AE$7:$AE$110,$AF$7:$AF$110,AI15) -> 67069621 | AL15: =AJ15+AK15 -> 67069621
A16: 3 | B16: 2025-26 | C16: Expense | D16: Fno Charges | E16: -4109562.8 | J16: Expense | K16: -2175687.1 | V16: Affluence High Risk | W16: 5128618.5 | AD16: =V25 -> YG | AE16: =W25 -> 30312620 | AF16: On
A17: 3 | B17: 2025-26 | C17: Revenue | D17: MCX Profits | E17: 60547800 | J17: Audit/Professional Fees | K17: -144780 | V17: FD | W17: 23500000 | Z17: Adjusting EQ Holdings | AA17: 0 | AD17: =V26 -> Yogita Agrawal PMS | AE17: =W26 -> 40685877 | AF17: On
A18: 3 | B18: 2025-26 | C18: Expense | D18: MCX Charges | E18: -195217.63 | J18: Equity and Non Equity Other Debits | K18: -9594.1988 | V18: HDFC Bank RN | W18: 1550293 | Z18: Adjusting MF Holdings | AA18: =-('Holdings Summary'!T19-'Holdings Summary'!AB9) -> -1.8292518e+08 | AD18: =V27 -> Zerodha Broking RN: Cash | AE18: =W27 -> 14852 | AF18: On
A19: 3 | B19: 2025-26 | C19: Revenue | D19: FnO Open Positions End of Year | E19: 0 | G19: -40702648 | J19: Fno Charges | K19: -1252925.9 | V19: ICICI Bank OD | W19: 48398458 | AD19: =V28 -> Zerodha Broking RN: Debt Mutual Funds | AE19: =W28 -> 3946196.5 | AF19: Off
A20: 3 | B20: 2025-26 | C20: Revenue | D20: FnO Open Positions Start of Year | E20: 15847722 | J20: Salary | K20: -706750 | V20: Interest Hand | W20: 0 | AD20: =V29 -> Zerodha Broking RN: EQ Holdings | AE20: =W29 -> 1.0744806e+08 | AF20: On
A21: 2 | B21: 2024-25 | C21: Revenue | D21: Consultancy Fees | E21: 12257627 | J21: Others | K21: -61637 | V21: Loan to Vihaan | W21: 3000000 | AD21: =V30 -> Zerodha Broking RN: EQ Mutual Funds | AE21: =W30 -> 0 | AF21: On
A22: 2 | B22: 2024-25 | C22: Revenue | D22: Other | E22: 5221.78 | J22: Revenue | K22: 14207815 | V22: PMS QFH Strategy | W22: 6092676 | AD22: =V31 -> Aurus Alpha Profit | AE22: =W31 -> 42915812 | AF22: On
A23: 1 | B23: 2023-24 | C23: Expense | D23: Audit/Professional Fees | E23: -63743 | J23: Consultancy Fees | K23: 12257627 | V23: Sushila Nahar Equity MF | W23: 15368350 | AD23: =V32 -> Marwadi Deposit | AE23: =W32 -> 10200000 | AF23: On
A24: 2 | B24: 2024-25 | C24: Expense | D24: Audit/Professional Fees | E24: -144780 | J24: Equity and Non Equity Profits | K24: 31 | V24: Swan Capital | W24: 5881036 | AD24: =V33 -> Marwadi Profits | AE24: =W33 -> 39226199 | AF24: On
A25: 3 | B25: 2025-26 | C25: Expense | D25: Audit/Professional Fees | E25: -5782 | J25: Equity Dividends | K25: 0 | V25: YG | W25: 30312620 | AD25: =V34 -> Marwadi FPI Deposit (FD) | AE25: =W34 -> 2625000 | AF25: Off
A26: 1 | B26: 2023-24 | C26: Taxes | D26: Taxes | E26: -443467 | J26: FnO Open Positions End of Year | K26: -15847722 | V26: Yogita Agrawal PMS | W26: 40685877 | AD26: =V35 -> Marwadi FPI Profits | AE26: =W35 -> 15169806 | AF26: Off
A27: 2 | B27: 2024-25 | C27: Taxes | D27: Taxes | E27: -3126313 | J27: FnO Open Positions Start of Year | K27: 0 | V27: Zerodha Broking RN: Cash | W27: 14852 | AD27: =V36 -> Nimai FD | AE27: =W36 -> 0 | AF27: Off
A28: 3 | B28: 2025-26 | C28: Taxes | D28: Taxes | E28: 0 | J28: FnO Profits | K28: 17841191 | V28: Zerodha Broking RN: Debt Mutual Funds | W28: 3946196.5 | AD28: =V37 -> Arvind FD | AE28: =W37 -> 700000 | AF28: Off
A29: 2 | B29: 2024-25 | C29: Expense | D29: Salary | E29: -706750 | J29: Mutual Fund Profits | K29: -48533.882 | Q29: unrealised pnl | V29: Zerodha Broking RN: EQ Holdings | W29: 1.0744806e+08 | AD29: =V38 -> Sushila Nahar HDFC | AE29: =W38 -> 0 | AF29: Off
A30: 2 | B30: 2024-25 | C30: Expense | D30: Others | E30: -61637 | J30: Other | K30: 5221.78 | O30: Current Open Holdings value which were purchased in Mishayan | P30: =SUM(P31:P35) -> 91154088 | Q30: =SUM(Q31:Q35) -> 2550599.2 | V30: Zerodha Broking RN: EQ Mutual Funds | W30: 0 | AD30: =V39 -> Sushila Nahar Zerodha | AE30: =W39 -> 13500000 | AF30: Off
A31: 3 | B31: 2025-26 | C31: Expense | D31: Salary | E31: -633500 | J31: Taxes | K31: -3126313 | O31: ADITYA BIRLA SUN LIFE MONEY MANAGER FUND - DIRECT PLAN | P31: 30987326 | Q31: 988714 | V31: Aurus Alpha Profit | W31: 42915812 | AD31: =V40 -> Sumesh FD | AE31: =W40 -> 2500000 | AF31: Off
A32: 3 | B32: 2025-26 | C32: Expense | D32: Others | E32: -324443.52 | J32: Taxes | K32: -3126313 | O32: EDELWEISS NIFTY MIDCAP 150 MOMENTUM 50 INDEX FUND - DIRECT PLAN | P32: 7440385 | Q32: 692480 | V32: Marwadi Deposit | W32: 10200000
A33: 3 | B33: 2025-26 | C33: Revenue | D33: Consultancy Fees | E33: 10000000 | J33: 2025-26 | K33: 2.0014338e+08 | O33: HDFC NIFTY200 Momentum 30 Index Fund | P33: 4166308 | Q33: 418119 | V33: Marwadi Profits | W33: 39226199
A34: 3 | B34: 2025-26 | C34: Revenue | D34: Mcx Open Positions End of Year | E34: =--2032400.2 -> 2032400.2 | J34: Expense | K34: -5282056.6 | O34: LIC MF LIQUID FUND - DIRECT PLAN | P34: 40322052 | Q34: 324057 | V34: Marwadi FPI Deposit (FD) | W34: 2625000
A35: 3 | B35: 2025-26 | C35: Revenue | D35: Mcx Open Positions Start of Year | E35: 0 | J35: Audit/Professional Fees | K35: -5782 | O35: LIQUIDCASE | P35: =8110787.6+127229.2 -> 8238016.8 | Q35: =127229.2 -> 127229.2 | V35: Marwadi FPI Profits | W35: 15169806
A36: 3 | B36: 2025-26 | C36: Revenue | D36: Mcx Unrealised Fut pnl at End of Year | E36: 23130200 | J36: Equity and Non Equity Other Debits | K36: -13550.635 | V36: Nimai FD | W36: 0
J37: Fno Charges | K37: -4109562.8 | V37: Arvind FD | W37: 700000 | AD37: Adjusting EQ Holdings
J38: MCX Charges | K38: -195217.63 | O38: Unrealised Pnl | P38: =SUM(P39:P40) -> 26747539 | V38: Sushila Nahar HDFC | W38: 0 | AD38: Adjusting MF Holdings | AE38: ='Holdings Summary'!T19-'Holdings Summary'!AB9 -> 1.8292518e+08 | AF38: On
J39: Salary | K39: -633500 | O39: Fno | P39: 1584939 | V39: Sushila Nahar Zerodha | W39: 13500000
J40: Others | K40: -324443.52 | O40: Mcx | P40: =E34+E36 -> 25162600 | V40: Sumesh FD | W40: 2500000
J41: Revenue | K41: 2.0542544e+08 | V41: (blank)
J42: Consultancy Fees | K42: 10000000 | O42: cash | P42: 69266087 | V42: (blank)
J43: FnO Open Positions End of Year | K43: 0 | O43: holdings at cost | P43: =P30-Q30 -> 88603489 | V43: Deepak Nahar | W43: 0
J44: FnO Open Positions Start of Year | K44: 15847722 | P44: =P42+P43 -> 1.5786958e+08 | Q44: =K55-P44 -> 52372412 | V44: Jainam Allocation Deposit | W44: 0
J45: FnO Profits | K45: 93867317 | O45: cash in bank | P45: 4599310 | V45: Grand Total | W45: 9.657011e+08
J46: MCX Profits | K46: 60547800 | O46: GRD | P46: 5200000
J47: Mcx Open Positions End of Year | K47: 2032400.2 | O47: jainam | P47: 31500000
J48: Mcx Open Positions Start of Year | K48: 0 | P48: =SUM(P45:P47) -> 41299310
J49: Mcx Unrealised Fut pnl at End of Year | K49: 23130200 | O49: advance tax | P49: 9500000
J50: Taxes | K50: 0 | O50: fixed assets | P50: 1574212
J51: Taxes | K51: 0 | O51: cash in hand | P51: 50000
J52: (blank) | P52: =P49+P50+P51 -> 11124212
J53: (blank)
J54: (blank)
I55: cr | J55: Grand Total | K55: 2.1024199e+08 | P55: =P44+P48-P39+P52 -> 2.0870816e+08 | Q55: =K58-P55 -> 1533828.8 | R55: take holdings at market value
I57: cr | J57: rishabh loan | K57: =P4 -> 0
K58: =K55+P4 -> 2.1024199e+08

Sheet Holdings Summary
A1: Current Stock Holdings in Mishayan | E1: Current Stock Holdings in RN | I1: Holdings Initially Bought in Mishayan | L1: Holdings Initially Bought in RN | S1: Current Mutual Fund Holdings in Mishayan | W1: Current Mutual Fund Holdings in RN | AA1: Mutual Funds Initially Bought in Mishayan | AE1: Mutual Funds Initially Bought in RN
A3: Mastersheet Tag | B3: Stock Holdings | E3: Mastersheet Tag | F3: Personal Stock Holdings Zerodha | I3: Notes | J3: Bought in Mishayan | L3: Notes | M3: Bought in RN | S3: Mastersheet Tag | T3: Mutual Funds | W3: Mastersheet Tag | X3: Personal Mutual Funds Zerodha | AA3: Notes | AB3: Bought in Mishayan | AE3: Notes | AF3: (Multiple Items)
A5: Holdings | B5: Value | E5: Holdings | F5: Value | I5: Holdings | J5: Value | L5: Holdings | M5: Value | S5: Holdings | T5: Value | W5: Holdings | X5: Value | AA5: Holdings | AB5: Value | AE5: Holdings | AF5: Value
A6: Bought in Mishayan | B6: 24386167 | E6: Bought in RN | F6: 1.0744806e+08 | I6: Debt | J6: 20087829 | L6: Equity | M6: 1.0128501e+08 | S6: Bought in Mishayan | T6: 92406491 | W6: Bought in RN | X6: 3946196.5 | AA6: Debt | AB6: 92406491 | AE6: Debt | AF6: 47626022
A7: Debt | B7: 20087829 | E7: Equity | F7: 1.0128501e+08 | I7: LIQUIDCASE | J7: 20087829 | L7: ALLETEC-SM | M7: 1027440 | S7: ADITYA BIRLA SUN LIFE MONEY MANAGER FUND - DIRECT PLAN | T7: 51528623 | W7: LIC MF LIQUID FUND - DIRECT PLAN | X7: 3946196.5 | AA7: ADITYA BIRLA SUN LIFE MONEY MANAGER FUND - DIRECT PLAN | AB7: 51528623 | AE7: ADITYA BIRLA SUN LIFE LIQUID FUND - DIRECT PLAN | AF7: 5666626.8
A8: LIQUIDCASE | B8: 20087829 | E8: ALLETEC-SM | F8: 1027440 | I8: Equity | J8: 4298337.5 | L8: ALPEXSOLAR-SM | M8: 10842900 | S8: LIC MF LIQUID FUND - DIRECT PLAN | T8: 40877868 | W8: Grand Total | X8: 3946196.5 | AA8: LIC MF LIQUID FUND - DIRECT PLAN | AB8: 40877868 | AE8: LIC MF LIQUID FUND - DIRECT PLAN | AF8: 3946196.5
A9: Equity | B9: 4298337.5 | E9: ALPEXSOLAR-SM | F9: 10842900 | I9: EXHICON | J9: 4298337.5 | L9: BALUFORGE | M9: 1359213.8 | S9: Bought in RN and Loaned to Mishayan | T9: 1.8292518e+08 | AA9: Grand Total | AB9: 92406491 | AE9: TATA LIQUID FUND - DIRECT PLAN | AF9: 38013199
A10: EXHICON | B10: 4298337.5 | E10: BALUFORGE | F10: 1359213.8 | I10: Grand Total | J10: 24386167 | L10: BBOX | M10: 2052562.2 | S10: ADITYA BIRLA SUN LIFE LIQUID FUND - DIRECT PLAN | T10: 5666626.8 | AE10: Equity | AF10: 1.3924535e+08
A11: Grand Total | B11: 24386167 | E11: BBOX | F11: 2052562.2 | L11: CAPLIPOINT | M11: 1511517.6 | S11: AXIS NIFTY500 MOMENTUM 50 INDEX FUND - DIRECT PLAN | T11: 3658679.9 | AE11: AXIS NIFTY500 MOMENTUM 50 INDEX FUND - DIRECT PLAN | AF11: 3658679.9
E12: CAPLIPOINT | F12: 1511517.6 | L12: CUB | M12: 2279628.5 | S12: ICICI PRUDENTIAL NIFTY 100 LOW VOLATILITY 30 ETF FOF - DIRECT PLAN | T12: 29509719 | AE12: ICICI PRUDENTIAL NIFTY 100 LOW VOLATILITY 30 ETF FOF - DIRECT PLAN | AF12: 29509719
E13: CUB | F13: 2279628.5 | L13: DEEPAKFERT | M13: 1263716.2 | S13: KOTAK NIFTY 200 MOMENTUM 30 INDEX FUND - DIRECT PLAN | T13: 39996120 | AE13: KOTAK NIFTY 200 MOMENTUM 30 INDEX FUND - DIRECT PLAN | AF13: 39996120
E14: DEEPAKFERT | F14: 1263716.2 | L14: DYCL | M14: 1284227.6 | S14: MOTILAL OSWAL NIFTY 500 MOMENTUM 50 INDEX FUND - DIRECT PLAN | T14: 8390499.8 | AE14: MOTILAL OSWAL NIFTY 500 MOMENTUM 50 INDEX FUND - DIRECT PLAN | AF14: 8390499.8
E15: DYCL | F15: 1284227.6 | L15: HOMEFIRST | M15: 1513289.2 | S15: PARAG PARIKH ELSS TAX SAVER FUND - DIRECT PLAN | T15: 243120.85 | AE15: PARAG PARIKH ELSS TAX SAVER FUND - DIRECT PLAN | AF15: 243120.85
E16: HOMEFIRST | F16: 1513289.2 | L16: ICRA | M16: 1649046 | S16: QUANT LARGE CAP FUND - DIRECT PLAN | T16: 18067480 | AE16: QUANT LARGE CAP FUND - DIRECT PLAN | AF16: 18067480
E17: ICRA | F17: 1649046 | L17: IIFLCAPS | M17: 4912865.4 | S17: TATA LIQUID FUND - DIRECT PLAN | T17: 38013199 | AE17: TATA NIFTY MIDCAP 150 MOMENTUM 50 INDEX FUND - DIRECT PLAN | AF17: 39379733
E18: IIFLCAPS | F18: 4912865.4 | L18: INDIASHLTR | M18: 1595409.2 | S18: TATA NIFTY MIDCAP 150 MOMENTUM 50 INDEX FUND - DIRECT PLAN | T18: 39379733 | AE18: Grand Total | AF18: 1.8687137e+08
E19: INDIASHLTR | F19: 1595409.2 | L19: KARURVYSYA | M19: 2446471.8 | S19: Grand Total | T19: 2.7533167e+08
E20: KARURVYSYA | F20: 2446471.8 | L20: KPL | M20: 3194246.4
E21: KPL | F21: 3194246.4 | L21: KRBL | M21: 1290143.8
E22: KRBL | F22: 1290143.8 | L22: KRISHANA | M22: 1705914.6
E23: KRISHANA | F23: 1705914.6 | L23: MPSLTD | M23: 1342478.9
E24: MPSLTD | F24: 1342478.9 | L24: PENIND | M24: 1115123.8
E25: PENIND | F25: 1115123.8 | L25: POKARNA | M25: 1899432.4
E26: POKARNA | F26: 1899432.4 | L26: POWERMECH | M26: 1312887.2
E27: POWERMECH | F27: 1312887.2 | L27: REGENCY | M27: 11513024
E28: REGENCY | F28: 11513024 | L28: SBFC | M28: 1570171.7
E29: SBFC | F29: 1570171.7 | L29: SHAKTIPUMP | M29: 1164644.2 | W29: =T26+X19 -> 0
E30: SHAKTIPUMP | F30: 1164644.2 | L30: SHREEPUSHK | M30: 1635722.4
E31: SHREEPUSHK | F31: 1635722.4 | L31: SKIPPER | M31: 1298922.5
E32: SKIPPER | F32: 1298922.5 | L32: SRM | M32: 1541877.6
E33: SRM | F33: 1541877.6 | L33: STEELCAS | M33: 2077107.7
E34: STEELCAS | F34: 2077107.7 | L34: SUPRIYA | M34: 1695047.7
E35: SUPRIYA | F35: 1695047.7 | L35: SYNCOMF | M35: 1359858.9
E36: SYNCOMF | F36: 1359858.9 | L36: TCPLPACK | M36: 1383361
E37: TCPLPACK | F37: 1383361 | L37: WELCORP | M37: 1813395
E38: WELCORP | F38: 1813395 | L38: ZTECH-SM | M38: 1669800
E39: ZTECH-SM | F39: 1669800 | L39: MONIKA | M39: 4281200
E40: MONIKA | F40: 4281200 | L40: FISCHER | M40: 1815500
E41: FISCHER | F41: 1815500 | L41: CCAVENUE | M41: 3510000
... E48: GOLDBEES | F48: 6163056 | L48: Grand Total | M48: 1.0744806e+08
E49: Grand Total | F49: 1.0744806e+08

Sheet Networth Inputs
A1: Liquidity | M1: Debt: | T1: Networth:
A3: Sr. No. | B3: Category | C3: Particulars 1 | D3: Particulars 2 | E3: Equity / Debt / Cash | F3: Value | G3: Mishayan / Rishabh | H3: On / Off | I3: Data as of | J3: Attachment Available | M3: Sr. No. | N3: Category | O3: Particulars | P3: Value | Q3: Mishayan / Rishabh | T3: Particulars | U3: Value
A4: 1 | B4: Client Account | C4: Zerodha Broking RN | D4: Equity Holdings | E4: Equity | F4: =SUMIFS('Equity Holdings'!$K$4:$K$82,'Equity Holdings'!$G$4:$G$82,'Networth Inputs'!E4,'Equity Holdings'!$B$4:$B$82,"Personal Stock Holdings Zerodha") -> 96365514 | G4: Rishabh | H4: On | I4: 46112 | J4: Yes | M4: 1 | N4: Debt | O4: ICICI Bank OD | P4: 65000000 | Q4: Rishabh | T4: Liquidity | U4: =SUM(F4:F123) -> 9.1849659e+08
A5: =A4+1 -> 2 | B5: Client Account | C5: Zerodha Broking RN | D5: Debt Holdings | E5: Debt | F5: =SUMIFS('Equity Holdings'!$K$4:$K$82,'Equity Holdings'!$G$4:$G$82,'Networth Inputs'!E5,'Equity Holdings'!$B$4:$B$82,"Personal Stock Holdings Zerodha") -> 0 | G5: Rishabh | H5: On | I5: 46112 | J5: Yes | M5: 2 | N5: Debt | O5: Sumesh | P5: 2500000 | Q5: Rishabh | T5: Less: Debt | U5: =SUM(P4:P123) -> 67500000
A6: =A5+1 -> 3 | B6: Client Account | C6: Zerodha Broking RN | D6: Gold Holdings | E6: Gold | F6: =SUMIFS('Equity Holdings'!$K$4:$K$82,'Equity Holdings'!$G$4:$G$82,'Networth Inputs'!E6,'Equity Holdings'!$B$4:$B$82,"Personal Stock Holdings Zerodha") -> 6156452 | G6: Rishabh | H6: On | I6: 46112 | J6: Yes | T6: Networth | U6: =U4-U5 -> 8.5099659e+08
A7: =A6+1 -> 4 | B7: Client Account | C7: Zerodha Broking RN | D7: Equity Mutual Fund Holdings | E7: Equity | F7: =SUMIFS('Mutual Funds'!$L$4:$L$92,'Mutual Funds'!$G$4:$G$92,'Networth Inputs'!E7,'Mutual Funds'!$H$4:$H$92,"Personal Mutual Funds Zerodha") -> 1.3401375e+08 | G7: Rishabh | H7: On | I7: 46112 | J7: Yes
A8: =A7+1 -> 5 | B8: Client Account | C8: Zerodha Broking RN | D8: Debt Mutual Fund Holdings | E8: Debt | F8: =SUMIFS('Mutual Funds'!$L$4:$L$92,'Mutual Funds'!$G$4:$G$92,'Networth Inputs'!E8,'Mutual Funds'!$H$4:$H$92,"Personal Mutual Funds Zerodha") -> 0 | G8: Rishabh | H8: On | I8: 46112 | J8: Yes
A9: =A8+1 -> 6 | B9: Client Account | C9: Zerodha Broking RN | D9: Cash | E9: Cash | F9: 1014842.1 | G9: Rishabh | H9: On | I9: 46112 | J9: No
A10: =A9+1 -> 7 | B10: Client Account | C10: Zerodha Broking RN | D10: Contract Value | E10: Cash | F10: 0 | G10: Rishabh | H10: On | I10: 46112 | J10: No
A12: =A10+1 -> 8 | B12: Client Account | C12: Zerodha Broking Mishayan | D12: Equity Holdings | E12: Equity | F12: =SUMIFS('Equity Holdings'!$K$4:$K$82,'Equity Holdings'!$G$4:$G$82,'Networth Inputs'!E12,'Equity Holdings'!$B$4:$B$82,"Stock Holdings") -> 2663212 | G12: Mishayan | H12: On | I12: 46112 | J12: Yes
A13: =A12+1 -> 9 | B13: Client Account | C13: Zerodha Broking Mishayan | D13: Debt Holdings | E13: Debt | F13: =SUMIFS('Equity Holdings'!$K$4:$K$82,'Equity Holdings'!$G$4:$G$82,'Networth Inputs'!E13,'Equity Holdings'!$B$4:$B$82,"Stock Holdings") -> 0 | G13: Mishayan | H13: On | I13: 46112 | J13: Yes
A14: =A13+1 -> 10 | B14: Client Account | C14: Zerodha Broking Mishayan | D14: Gold Holdings | E14: Gold | F14: =SUMIFS('Equity Holdings'!$K$4:$K$82,'Equity Holdings'!$G$4:$G$82,'Networth Inputs'!E14,'Equity Holdings'!$B$4:$B$82,"Stock Holdings") -> 0 | G14: Mishayan | H14: On | I14: 46112 | J14: Yes
A15: =A14+1 -> 11 | B15: Client Account | C15: Zerodha Broking Mishayan | D15: Equity Mutual Fund Holdings | E15: Equity | F15: =SUMIFS('Mutual Funds'!$L$4:$L$92,'Mutual Funds'!$G$4:$G$92,'Networth Inputs'!E15,'Mutual Funds'!$H$4:$H$92,"Mutual Funds") -> 0 | G15: Mishayan | H15: On | I15: 46112 | J15: Yes
A16: =A15+1 -> 12 | B16: Client Account | C16: Zerodha Broking Mishayan | D16: Debt Mutual Fund Holdings | E16: Debt | F16: =SUMIFS('Mutual Funds'!$L$4:$L$92,'Mutual Funds'!$G$4:$G$92,'Networth Inputs'!E16,'Mutual Funds'!$H$4:$H$92,"Mutual Funds") -> 1.1272582e+08 | G16: Mishayan | H16: On | I16: 46112 | J16: Yes
A17: =A16+1 -> 13 | B17: Client Account | C17: Zerodha Broking Mishayan | D17: Cash | E17: Cash | F17: =75890878.49 -> 75890878 | G17: Mishayan | H17: On | I17: 46112 | J17: No
A18: =A17+1 -> 14 | B18: Client Account | C18: Zerodha Broking Mishayan | D18: Contract Value | E18: Cash | F18: 201357611 | G18: Mishayan | H18: On | I18: 46112 | J18: No
A20: =A18+1 -> 15 | B20: Prop | C20: Jainam | D20: Jainam - Deposit | E20: Debt | F20: 31500000 | G20: Mishayan | H20: On | I20: 46112 | J20: No
A21: =A20+1 -> 16 | B21: Prop | C21: Jainam | D21: Jainam - Profit and Loss | E21: Debt | F21: 35000000 | G21: Rishabh | H21: Off | I21: 46112 | J21: No
A22: =A21+1 -> 17 | B22: Prop | C22: Jainam | D22: Jainam - Allocation Deposit | E22: Debt | F22: 0 | G22: Rishabh | H22: Off | I22: 46112 | J22: No
A23: =A22+1 -> 18 | B23: Prop | C23: Marwadi Prop | D23: Marwadi Prop - Deposit | E23: Debt | F23: 10200000 | G23: Rishabh | H23: Off | I23: 46112 | J23: No
A24: =A23+1 -> 19 | B24: Prop | C24: Marwadi Prop | D24: Marwadi Prop - Profit and Loss | E24: Debt | F24: =34978573.9+251926.56 -> 35230500 | G24: Rishabh | H24: Off | I24: 46112 | J24: No
A25: =A24+1 -> 20 | B25: Prop | C25: Marwadi FPI | D25: Marwadi FPI - Deposit | E25: Debt | F25: 2625000 | G25: Rishabh | H25: Off | I25: 46112 | J25: No
A26: =A25+1 -> 21 | B26: Prop | C26: Marwadi FPI | D26: Marwadi FPI - Profit and Loss | E26: Debt | F26: =13482336.48+6.3%*(-68598797) -> 9160612.3 | G26: Rishabh | H26: On | I26: 46112 | J26: No
A27: =A26+1 -> 22 | B27: Prop | C27: Affluence Prop | D27: Affluence Prop - Deposit | E27: Debt | F27: 0 | G27: Rishabh | H27: On | I27: 46112 | J27: No
A28: =A27+1 -> 23 | B28: Prop | C28: Affluence Prop | D28: Affluence Prop - Profit and Loss | E28: Debt | F28: =5906672.74+-1197579 -> 4709093.7 | G28: Rishabh | H28: On | I28: 46108 | J28: No
A29: =A28+1 -> 24 | B29: Prop | C29: Affluence High Risk | D29: Affluence High Risk - Deposit | E29: Debt | F29: 0 | G29: Rishabh | H29: On | I29: 46112 | J29: No
A30: =A29+1 -> 25 | B30: Prop | C30: Affluence High Risk | D30: Affluence High Risk - Profit and Loss | E30: Debt | F30: =746770.22+1108983.82+2872822.57+6375938*30%*35% -> 5398050.1 | G30: Rishabh | H30: On | I30: 46112 | J30: No
A31: =A30+1 -> 26 | B31: Prop | C31: Ashika Prop | D31: Ashika Prop - Deposit | E31: Debt | F31: 0 | G31: Rishabh | H31: On | I31: 46112 | J31: No
A32: =A31+1 -> 27 | B32: Prop | C32: Ashika Prop | D32: Ashika Prop - Profit and Loss | E32: Debt | F32: =393914.3+-20567.7+(81218+90278)*20%*35% -> 385351.32 | G32: Rishabh | H32: On | I32: 46112 | J32: No
A33: =A32+1 -> 28 | B33: Prop | C33: SRE | D33: Deposit | E33: Debt | F33: 2500000 | G33: Rishabh | H33: On | I33: 46112 | J33: No
A34: =A33+1 -> 29 | B34: Prop | C34: SRE | D34: Profit and Loss | E34: Debt | F34: =-2499611.53+(22991024.73-6966176.5)*60% -> 7115297.4 | G34: Rishabh | H34: Off | I34: 46112 | J34: No
A35: =A34+1 -> 30 | B35: Prop | C35: Jainam FPI | D35: Deposit | E35: Debt | F35: 10000000 | G35: Rishabh | H35: Off | I35: 46112 | J35: No
A36: =A35+1 -> 31 | B36: Prop | C36: Jainam FPI | D36: Profit and Loss | E36: Debt | F36: 0 | G36: Rishabh | H36: Off | I36: 46112 | J36: No
A37: =A36+1 -> 32 | B37: Prop | C37: Rishabh Jainam Prop | D37: Profit and Loss | E37: Debt | F37: 17236946 | G37: Rishabh | H37: Off | I37: 46112 | J37: No
A39: =A37+1 -> 33 | B39: Other Investments | C39: Sushila Nahar Equity MF | D39: Sushila Nahar Equity MF | E39: Equity | F39: 15014887 | G39: Rishabh | H39: On | I39: 46112 | J39: No
A40: =A39+1 -> 34 | B40: Other Investments | C40: Yogita Agrawal Qode PMS | D40: Yogita Agrawal Qode PMS - QMF | E40: Equity | F40: 10279400 | G40: Rishabh | H40: On | I40: 46112 | J40: No
A41: =A40+1 -> 35 | B41: Other Investments | C41: Yogita Agrawal Qode PMS | D41: Yogita Agrawal Qode PMS - QTF | E41: Equity | F41: 5349685.4 | G41: Rishabh | H41: On | I41: 46112 | J41: No
A42: =A41+1 -> 36 | B42: Other Investments | C42: Yogita Agrawal Qode PMS | D42: Yogita Agrawal Qode PMS - QAW | E42: Equity | F42: 23981288 | G42: Rishabh | H42: On | I42: 46112 | J42: No
A43: =A42+1 -> 37 | B43: Other Investments | C43: Loan to Vihaan | D43: Loan to Vihaan | E43: Debt | F43: 3000000 | G43: Rishabh | H43: On | I43: 46112 | J43: No
A44: =A43+1 -> 38 | B44: Other Investments | C44: Rishabh Nahar Qode PMS | D44: Rishabh Nahar Qode PMS - QFH | E44: Equity | F44: 5687110 | G44: Rishabh | H44: On | I44: 46112 | J44: No
A45: =A44+1 -> 39 | B45: Other Investments | C45: Swan Capital | D45: Swan Capital | E45: Debt | F45: 5881036 | G45: Rishabh | H45: On | I45: 46112 | J45: No
A46: =A45+1 -> 40 | B46: Other Investments | C46: Sushila Nahar HDFC | D46: Sushila Nahar HDFC | E46: Equity | F46: 0 | G46: Rishabh | H46: On | I46: 46112 | J46: No
A47: =A46+1 -> 41 | B47: Other Investments | C47: Sushila Nahar Zerodha | D47: Sushila Nahar Zerodha | E47: Equity | F47: 11699620 | G47: Rishabh | H47: On | I47: 46112 | J47: No
A49: =A47+1 -> 42 | B49: FD | C49: Cash in Bank | D49: HDFC Bank RN | E49: Cash | F49: =898983.05+5000000 -> 5898983 | G49: Rishabh | H49: On | I49: 46112 | J49: No
A50: =A49+1 -> 43 | B50: FD | C50: Cash in Bank | D50: HDFC Bank Mishayan | E50: Cash | F50: 1857193 | G50: Mishayan | H50: On | I50: 46112 | J50: No
A51: =A50+1 -> 44 | B51: FD | C51: FD | D51: FD | E51: Debt | F51: 23500000 | G51: Rishabh | H51: Off | I51: 46112 | J51: No
A52: =A51+1 -> 45 | B52: FD | C52: OD | D52: ICICI Bank OD | E52: Debt | F52: 898458 | G52: Rishabh | H52: On | I52: 46112 | J52: No
A53: =A52+1 -> 46 | B53: FD | C53: FD | D53: HDFC Bank FD | E53: Debt | F53: 1000000 | G53: Mishayan | H53: On | I53: 46112 | J53: No
A54: =A53+1 -> 47 | B54: FD | C54: FD | D54: Arvind FD | E54: Debt | F54: 700000 | G54: Rishabh | H54: Off | I54: 46112 | J54: No
A55: =A54+1 -> 48 | B55: FD | C55: FD | D55: Sumesh FD | E55: Debt | F55: 2500000 | G55: Rishabh | H55: Off | I55: 46112 | J55: No

Sheet Cash and Margin
A1: Total Exposure in Mishayan for Long & Psar: | J1: Inputs: | P1: Cash and Non Cash Component | Z1: Mishayan | AC1: Rishabh
Z2: Current Cash in Mishayan | AA2: =U5 -> 2.7724849e+08 | AC2: Cash in Zerodha | AD2: ='Networth Inputs'!F9+'Networth Inputs'!F10 -> 1014842.1
A3: Sr. No. | B3: Particulars | C3: Value | E3: Sr. No. | F3: Particulars | G3: Value | J3: Sr. No. | K3: Particulars | L3: Input | P3: Sr. No. | Q3: System | R3: Cash Component (Liquid Funds) | S3: Non Cash Component | T3: Liquidcase | U3: Cash | V3: Total | W3: Total % of PV | Z3: Buy Debt mutual fund | AA3: =-R7/0.9 -> 20707981 | AC3: Cash in Bank | AD3: 5000000
A4: 1 | B4: Zerodha Broking RN | C4: =SUM('Networth Inputs'!F4:F10) -> 2.3755056e+08 | E4: 1 | F4: Current Gold Exposure | G4: =21*100*147666 -> 310098600 | J4: 1 | K4: Long Options PS | L4: 0.015 | Z4: Buy Liquidcase | AA4: =-T7 -> 11956746 | AC4: Jainam Deposit | AD4: 31500000
A5: =A4+1 -> 2 | B5: Zerodha Broking Mishayan | C5: =SUM('Networth Inputs'!F12:F18) -> 3.9263752e+08 | E5: =E4+1 -> 2 | F5: Ideal Gold Exposure | G5: =SUMIFS('Networth Inputs'!$F$4:$F$18,'Networth Inputs'!$E$4:$E$18,"Debt")+SUMIFS('Networth Inputs'!$F$39:$F$94,'Networth Inputs'!$E$39:$E$94,"Debt") -> 1.5020531e+08 | H5: based on debt | J5: =J4+1 -> 2 | K5: PSAR Multiplier | L5: 2.1 | P5: 1 | Q5: Available on Zerodha | R5: =101363742-0.94*T5 -> 101363742 | S5: 0 | T5: =VLOOKUP("Zerodha Broking Mishayan: Liquidbees/ Liquidcase",'Networth Inputs - old'!$C$4:$E$114,3,FALSE) -> 0 | U5: ='Networth Inputs'!F17+'Networth Inputs'!F18 -> 2.7724849e+08 | V5: =SUM(R5:U5) -> 3.7861223e+08 | W5: =V5/$C$22 -> 0.5277526 | Z5: Keep Cash | AA5: =U6 -> 43996263 | AC5: Mishayan Loan Repayment | AD5: =50000000-31500000 -> 18500000
A6: =A5+1 -> 3 | B6: ='Networth Inputs'!D39 -> Sushila Nahar Equity MF | C6: ='Networth Inputs'!F39 -> 15014887 | E6: =E5+1 -> 3 | F6: Put Protection Exposure | G6: =SUMIFS('Networth Inputs'!$F$4:$F$18,'Networth Inputs'!$E$4:$E$18,"Equity") -> 2.3304248e+08 | H6: equities in zerodha | J6: =J5+1 -> 3 | K6: Psar Leverage | L6: 8 | P6: =P5+1 -> 2 | Q6: Total Required | R6: =SUM(R9:R16) -> 1.2000092e+08 | S6: =SUM(S9:S16) -> 1.2000092e+08 | T6: =SUM(T9:T16) -> 11956746 | U6: =SUM(U9:U16) -> 43996263 | V6: =SUM(V9:V16) -> 2.9595486e+08 | W6: =V6/$C$22 -> 0.4125354 | Z6: Balance Cash Available | AA6: =AA2-AA3-AA4-AA5 -> 2.005875e+08 | AC6: Cash Available to deploy in Equity | AD6: =SUM(AD2:AD5) -> 56014842
A7: =A6+1 -> 4 | B7: ='Networth Inputs'!D40 -> Yogita Agrawal Qode PMS - QMF | C7: ='Networth Inputs'!F40 -> 10279400 | J7: =J6+1 -> 4 | K7: Cash Drawdown Margin | L7: =5%*2/3 -> 0.033333333 | P7: =P6+1 -> 3 | Q7: Margin Excess/Shortfall | R7: =R5-R6 -> -18637183 | S7: =S5-S6 -> -1.2000092e+08 | T7: =T5-T6 -> -11956746 | U7: =U5-U6 -> 2.3325223e+08 | V7: =SUM(R7:U7) -> 82657373 | W7: =V7/$C$22 -> 0.11521721 | Z7: Reverse loan to RN | AA7: =50000000-31500000 -> 18500000
A8: =A7+1 -> 5 | B8: ='Networth Inputs'!D43 -> Loan to Vihaan | C8: ='Networth Inputs'!F43 -> 3000000 | J8: =J7+1 -> 5 | K8: Liquidbees Drawdown Margin | L8: =5%*1/3 -> 0.016666667 | Z8: Outstanding OD - Actual | AA8: 65000000
A9: =A8+1 -> 6 | B9: ='Networth Inputs'!D44 -> Rishabh Nahar Qode PMS - QFH | C9: ='Networth Inputs'!F44 -> 5687110 | J9: =J8+1 -> 6 | K9: DMA Cash Requirement | L9: 0.04 | P9: 1 | Q9: Cash Drawdown Margin | U9: =L7*C22 -> 23913492 | V9: =SUM(R9:U9) -> 23913492 | W9: =V9/$C$22 -> 0.033333333 | Z9: Currently Payback OD | AA9: =32500000-4400000 -> 28100000
A10: =A9+1 -> 7 | B10: ='Networth Inputs'!D45 -> Swan Capital | C10: ='Networth Inputs'!F45 -> 5881036 | J10: =J9+1 -> 7 | K10: Gold Fut Leverage | L10: 6 | P10: =P9+1 -> 2 | Q10: Liquidbees Drawdown Margin | T10: =L8*C22 -> 11956746 | V10: =SUM(R10:U10) -> 11956746 | W10: =V10/$C$22 -> 0.016666667 | Z10: Expenses | AA10: 6000000
A11: =A10+1 -> 8 | B11: ='Networth Inputs'!D46 -> Sushila Nahar HDFC | C11: ='Networth Inputs'!F46 -> 0 | J11: =J10+1 -> 8 | Z11: Cash Available to deploy in Equity | AA11: =AA6-AA7-AA9-AA10 -> 1.479875e+08
A12: =A11+1 -> 9 | B12: ='Networth Inputs'!D47 -> Sushila Nahar Zerodha | C12: ='Networth Inputs'!F47 -> 11699620 | J12: =J11+1 -> 9 | P12: 1 | Q12: Long Options | U12: =L4*C22 -> 10761071 | V12: =SUM(R12:U12) -> 10761071 | W12: =V12/$C$22 -> 0.015
A13: =A12+1 -> 10 | B13: ='Networth Inputs'!D49 -> HDFC Bank RN | C13: ='Networth Inputs'!F49 -> 5898983 | J13: =J12+1 -> 10 | P13: =P12+1 -> 2 | Q13: PSAR | R13: =$C$22*$L$5/$L$6/2 -> 94159375 | S13: =$C$22*$L$5/$L$6/2 -> 94159375 | V13: =SUM(R13:U13) -> 1.8831875e+08 | W13: =V13/$C$22 -> 0.2625
A14: =A13+1 -> 11 | B14: ='Networth Inputs'!D50 -> HDFC Bank Mishayan | C14: ='Networth Inputs'!F50 -> 1857193 | P14: =P13+1 -> 3 | Q14: DMA | U14: =$L$9*G6 -> 9321699 | V14: =SUM(R14:U14) -> 9321699 | W14: =V14/$C$22 -> 0.01299364 | Z14: note: if expenses increase reduce od repayment amount
A15: =A14+1 -> 12 | B15: ='Networth Inputs'!D51 -> FD | C15: ='Networth Inputs'!F51 -> 23500000 | P15: =P14+1 -> 4 | Q15: Gold Fut | R15: =$G$4/$L$10/2 -> 25841550 | S15: =$G$4/$L$10/2 -> 25841550 | V15: =SUM(R15:U15) -> 51683100 | W15: =V15/$C$22 -> 0.072041758
A16: =A15+1 -> 13 | B16: ='Networth Inputs'!D52 -> ICICI Bank OD | C16: ='Networth Inputs'!F52 -> 898458
A17: =A16+1 -> 14 | B17: ='Networth Inputs'!D53 -> HDFC Bank FD | C17: ='Networth Inputs'!F53 -> 1000000 | J17: Note: | K17: Cash + DD Margin for 3x psar is 15%
A18: =A17+1 -> 15 | B18: ='Networth Inputs'!D55 -> Sumesh FD | C18: ='Networth Inputs'!F55 -> 2500000 | K18: Cash + DD Margin for 2x psar is 5%
A19: =A18+1 -> 16 | B19: ='Networth Inputs'!D56 -> 0 | C19: ='Networth Inputs'!F56 -> 0 | K19: Cash:LBS Ratio will always be 2:1 | Q19: Total Capital Required in Mishayan | R19: =R6/0.88 -> 1.3636469e+08 | S19: =S6/0.88 -> 1.3636469e+08 | T19: =T6 -> 11956746 | U19: =U6 -> 43996263 | V19: =SUM(R19:U19) -> 3.2868238e+08 | W19: =V19/C22 -> 0.45815473
A20: =A19+1 -> 17 | V20: 340000000
A21: =A20+1 -> 18
B22: Total | C22: =SUM(C4:C21) -> 7.1740476e+08

Sheet Strategy Allocation
A2: Sr. No. | B2: Account | C2: Strategy | D2: Position Sizing | E2: Tag | F2: Portoflio Value | G2: % Share | H2: Exposure | I2: Net Exposure | J2: Long Options Premium
A3: 1 | B3: Zerodha Broking Mishayan | C3: Long Options | D3: 0.015 | E3: Derivatives | F3: ='Cash and Margin'!$C$22 -> 7.1740476e+08 | G3: 1 | H3: =G3*F3 -> 7.1740476e+08 | I3: =H3 -> 7.1740476e+08 | J3: =IF(C3="Long Options",D3*H3,0) -> 10761071
A4: =A3+1 -> 2 | B4: Zerodha Broking Mishayan | C4: PSAR | D4: 2.1 | E4: Derivatives | F4: ='Cash and Margin'!$C$22 -> 7.1740476e+08 | G4: 1 | H4: =G4*F4 -> 7.1740476e+08 | I4: =H4*D4 -> 1.50655e+09 | J4: =IF(C4="Long Options",D4*H4,0) -> 0
A5: =A4+1 -> 3 | B5: Zerodha Broking Mishayan | C5: QAW Futures | D5: 0 | E5: Equity | F5: ='Cash and Margin'!$C$22 -> 7.1740476e+08 | G5: 1 | H5: =G5*F5 -> 7.1740476e+08 | I5: =H5*D5 -> 0 | J5: =IF(C5="Long Options",D5*H5,0) -> 0
A6: =A5+1 -> 4 | B6: Zerodha Broking Mishayan | C6: Gold Futures | D6: =F6/'Cash and Margin'!C22 -> 0.43225055 | E6: Gold | F6: ='Cash and Margin'!G4 -> 310098600 | G6: 1 | H6: =G6*F6 -> 310098600 | I6: =H6*D6 -> 1.3404029e+08 | J6: =IF(C6="Long Options",D6*H6,0) -> 0
A7: =A6+1 -> 5 | B7: Zerodha Broking Mishayan | C7: Put Protection | D7: =F7/'Cash and Margin'!C22 -> 0.32484099 | E7: Derivatives | F7: ='Cash and Margin'!G6 -> 2.3304248e+08 | G7: 1 | H7: =G7*F7 -> 2.3304248e+08 | I7: =H7*D7 -> 75701750 | J7: =IF(C7="Long Options",D7*H7,0) -> 0
A9: =A7+1 -> 6 | B9: Affluence High Risk | C9: Long Options | D9: 0.02 | E9: Derivatives | F9: 201259165 | G9: =30%*35% -> 0.105 | H9: =G9*F9 -> 21132212 | I9: =H9 -> 21132212 | J9: =IF(C9="Long Options",D9*H9,0) -> 422644.25
A10: =A9+1 -> 7 | B10: Affluence High Risk | C10: PSAR | D10: 3 | E10: Derivatives | F10: 201259165 | G10: =30%*35% -> 0.105 | H10: =G10*F10 -> 21132212 | I10: =H10*D10 -> 63396637 | J10: =IF(C10="Long Options",D10*H10,0) -> 0
A11: =A10+1 -> 8 | B11: Affluence High Risk | C11: QAW Futures | D11: 0 | E11: Equity | F11: 201259165 | G11: =30%*35% -> 0.105 | H11: =G11*F11 -> 21132212 | I11: =H11*D11 -> 0 | J11: =IF(C11="Long Options",D11*H11,0) -> 0
A12: =A11+1 -> 9 | B12: Affluence High Risk | C12: Gold Futures | D12: 0 | E12: Gold | F12: 201259165 | G12: =30%*35% -> 0.105 | H12: =G12*F12 -> 21132212 | I12: =H12*D12 -> 0 | J12: =IF(C12="Long Options",D12*H12,0) -> 0
A13: =A12+1 -> 10 | B13: Affluence High Risk | C13: Put Protection | D13: 0 | E13: Derivatives | F13: 201259165 | G13: =30%*35% -> 0.105 | H13: =G13*F13 -> 21132212 | I13: =H13*D13 -> 0 | J13: =IF(C13="Long Options",D13*H13,0) -> 0
A15: =A13+1 -> 11 | B15: Affluence Prop | C15: Long Options | D15: 0.015 | E15: Derivatives | F15: 247987850 | G15: =30%*35% -> 0.105 | H15: =G15*F15 -> 26038724 | I15: =H15 -> 26038724 | J15: =IF(C15="Long Options",D15*H15,0) -> 390580.86
A16: =A15+1 -> 12 | B16: Affluence Prop | C16: PSAR | D16: 3 | E16: Derivatives | F16: 247987850 | G16: =30%*35% -> 0.105 | H16: =G16*F16 -> 26038724 | I16: =H16*D16 -> 78116173 | J16: =IF(C16="Long Options",D16*H16,0) -> 0
A17: =A16+1 -> 13 | B17: Affluence Prop | C17: QAW Futures | D17: 0.6 | E17: Equity | F17: 247987850 | G17: =30%*35% -> 0.105 | H17: =G17*F17 -> 26038724 | I17: =H17*D17 -> 15623235 | J17: =IF(C17="Long Options",D17*H17,0) -> 0 | L17: stock futures of jay not added as we will be stopping it
A18: =A17+1 -> 14 | B18: Affluence Prop | C18: Gold Futures | D18: 0.4 | E18: Gold | F18: 247987850 | G18: =30%*35% -> 0.105 | H18: =G18*F18 -> 26038724 | I18: =H18*D18 -> 10415490 | J18: =IF(C18="Long Options",D18*H18,0) -> 0
A19: =A18+1 -> 15 | B19: Affluence Prop | C19: Put Protection | D19: 0.6 | E19: Derivatives | F19: 247987850 | G19: =30%*35% -> 0.105 | H19: =G19*F19 -> 26038724 | I19: =H19*D19 -> 15623235 | J19: =IF(C19="Long Options",D19*H19,0) -> 0
A21: =A19+1 -> 16 | B21: Ashika Prop | C21: Long Options | D21: 0.015 | E21: Derivatives | F21: =49255956+49806019 -> 99061975 | G21: =20%*35% -> 0.07 | H21: =G21*F21 -> 6934338.2 | I21: =H21 -> 6934338.2 | J21: =IF(C21="Long Options",D21*H21,0) -> 104015.07
A22: =A21+1 -> 17 | B22: Ashika Prop | C22: PSAR | D22: 2 | E22: Derivatives | F22: =49255956+49806019 -> 99061975 | G22: =20%*35% -> 0.07 | H22: =G22*F22 -> 6934338.2 | I22: =H22*D22 -> 13868676 | J22: =IF(C22="Long Options",D22*H22,0) -> 0
A23: =A22+1 -> 18 | B23: Ashika Prop | C23: QAW Futures | D23: 0 | E23: Equity | F23: =49255956+49806019 -> 99061975 | G23: =20%*35% -> 0.07 | H23: =G23*F23 -> 6934338.2 | I23: =H23*D23 -> 0 | J23: =IF(C23="Long Options",D23*H23,0) -> 0
A24: =A23+1 -> 19 | B24: Ashika Prop | C24: Gold Futures | D24: 0 | E24: Gold | F24: =49255956+49806019 -> 99061975 | G24: =20%*35% -> 0.07 | H24: =G24*F24 -> 6934338.2 | I24: =H24*D24 -> 0 | J24: =IF(C24="Long Options",D24*H24,0) -> 0
A25: =A24+1 -> 20 | B25: Ashika Prop | C25: Put Protection | D25: 0 | E25: Derivatives | F25: =49255956+49806019 -> 99061975 | G25: =20%*35% -> 0.07 | H25: =G25*F25 -> 6934338.2 | I25: =H25*D25 -> 0 | J25: =IF(C25="Long Options",D25*H25,0) -> 0
A27: =A25+1 -> 21 | B27: Marwadi Prop | C27: Long Options | D27: 0.015 | E27: Derivatives | F27: 1675163442 | G27: 0.1277 | H27: =G27*F27 -> 2.1391837e+08 | I27: =H27 -> 2.1391837e+08 | J27: =IF(C27="Long Options",D27*H27,0) -> 3208775.6
A28: =A27+1 -> 22 | B28: Marwadi Prop | C28: PSAR | D28: 3 | E28: Derivatives | F28: 1675163442 | G28: 0.1277 | H28: =G28*F28 -> 2.1391837e+08 | I28: =H28*D28 -> 6.4175511e+08 | J28: =IF(C28="Long Options",D28*H28,0) -> 0
A29: =A28+1 -> 23 | B29: Marwadi Prop | C29: QAW Futures | D29: 0.6 | E29: Equity | F29: 1675163442 | G29: 0.1277 | H29: =G29*F29 -> 2.1391837e+08 | I29: =H29*D29 -> 1.2835102e+08 | J29: =IF(C29="Long Options",D29*H29,0) -> 0 | L29: stock futures of jay not added as we will be stopping it
A30: =A29+1 -> 24 | B30: Marwadi Prop | C30: Gold Futures | D30: 0.4 | E30: Gold | F30: 1675163442 | G30: 0.1277 | H30: =G30*F30 -> 2.1391837e+08 | I30: =H30*D30 -> 85567349 | J30: =IF(C30="Long Options",D30*H30,0) -> 0
A31: =A30+1 -> 25 | B31: Marwadi Prop | C31: Put Protection | D31: 0.6 | E31: Derivatives | F31: 1675163442 | G31: 0.1277 | H31: =G31*F31 -> 2.1391837e+08 | I31: =H31*D31 -> 1.2835102e+08 | J31: =IF(C31="Long Options",D31*H31,0) -> 0
A33: =A31+1 -> 26 | B33: Marwadi FPI | C33: Long Options | D33: 0.015 | E33: Derivatives | F33: 1444907803 | G33: 0.1277 | H33: =G33*F33 -> 1.8451473e+08 | I33: =H33 -> 1.8451473e+08 | J33: =IF(C33="Long Options",D33*H33,0) -> 2767720.9
A34: =A33+1 -> 27 | B34: Marwadi FPI | C34: PSAR | D34: 3 | E34: Derivatives | F34: 1444907803 | G34: 0.1277 | H34: =G34*F34 -> 1.8451473e+08 | I34: =H34*D34 -> 5.5354418e+08 | J34: =IF(C34="Long Options",D34*H34,0) -> 0
A35: =A34+1 -> 28 | B35: Marwadi FPI | C35: QAW Futures | D35: 0.6 | E35: Equity | F35: 1444907803 | G35: 0.1277 | H35: =G35*F35 -> 1.8451473e+08 | I35: =H35*D35 -> 1.1070884e+08 | J35: =IF(C35="Long Options",D35*H35,0) -> 0
A36: =A35+1 -> 29 | B36: Marwadi FPI | C36: Gold Futures | D36: 0.4 | E36: Gold | F36: 1444907803 | G36: 0.1277 | H36: =G36*F36 -> 1.8451473e+08 | I36: =H36*D36 -> 73805891 | J36: =IF(C36="Long Options",D36*H36,0) -> 0
A37: =A36+1 -> 30 | B37: Marwadi FPI | C37: Put Protection | D37: 0.6 | E37: Derivatives | F37: 1444907803 | G37: 0.1277 | H37: =G37*F37 -> 1.8451473e+08 | I37: =H37*D37 -> 1.1070884e+08 | J37: =IF(C37="Long Options",D37*H37,0) -> 0
A39: =A37+1 -> 31 | B39: SRE | C39: Long Options | D39: 0.015 | E39: Derivatives | F39: 192933020 | G39: 0.6 | H39: =G39*F39 -> 115759812 | I39: =H39 -> 115759812 | J39: =IF(C39="Long Options",D39*H39,0) -> 1736397.2
A40: =A39+1 -> 32 | B40: SRE | C40: PSAR | D40: 2 | E40: Derivatives | F40: 192933020 | G40: 0.6 | H40: =G40*F40 -> 115759812 | I40: =H40*D40 -> 231519624 | J40: =IF(C40="Long Options",D40*H40,0) -> 0
A41: =A40+1 -> 33 | B41: SRE | C41: QAW Futures | D41: 0.6 | E41: Equity | F41: 192933020 | G41: 0.6 | H41: =G41*F41 -> 115759812 | I41: =H41*D41 -> 69455887 | J41: =IF(C41="Long Options",D41*H41,0) -> 0
A42: =A41+1 -> 34 | B42: SRE | C42: Gold Futures | D42: 0 | E42: Gold | F42: 192933020 | G42: 0.6 | H42: =G42*F42 -> 115759812 | I42: =H42*D42 -> 0 | J42: =IF(C42="Long Options",D42*H42,0) -> 0
A43: =A42+1 -> 35 | B43: SRE | C43: Put Protection | D43: 0.6 | E43: Derivatives | F43: 192933020 | G43: 0.6 | H43: =G43*F43 -> 115759812 | I43: =H43*D43 -> 69455887 | J43: =IF(C43="Long Options",D43*H43,0) -> 0
A45: =A43+1 -> 36 | B45: Swan Jainam Prop | C45: Long Options | D45: 0.025 | E45: Derivatives | F45: =325741862+325763965 -> 651505827 | G45: 0.3576 | H45: =G45*F45 -> 2.3297848e+08 | I45: =H45 -> 2.3297848e+08 | J45: =IF(C45="Long Options",D45*H45,0) -> 5824462.1
A46: =A45+1 -> 37 | B46: Swan Jainam Prop | C46: PSAR | D46: 3.34 | E46: Derivatives | F46: =325741862+325763965 -> 651505827 | G46: 0.3576 | H46: =G46*F46 -> 2.3297848e+08 | I46: =H46*D46 -> 7.7814814e+08 | J46: =IF(C46="Long Options",D46*H46,0) -> 0
A47: =A46+1 -> 38 | B47: Swan Jainam Prop | C47: QAW Futures | D47: =60%*1.17 -> 0.702 | E47: Equity | F47: =325741862+325763965 -> 651505827 | G47: 0.3576 | H47: =G47*F47 -> 2.3297848e+08 | I47: =H47*D47 -> 1.635509e+08 | J47: =IF(C47="Long Options",D47*H47,0) -> 0
A48: =A47+1 -> 39 | B48: Swan Jainam Prop | C48: Gold Futures | D48: =40%*1.17 -> 0.468 | E48: Gold | F48: =325741862+325763965 -> 651505827 | G48: 0.3576 | H48: =G48*F48 -> 2.3297848e+08 | I48: =H48*D48 -> 1.0903393e+08 | J48: =IF(C48="Long Options",D48*H48,0) -> 0
A49: =A48+1 -> 40 | B49: Swan Jainam Prop | C49: Put Protection | D49: =60%*1.17 -> 0.702 | E49: Derivatives | F49: =325741862+325763965 -> 651505827 | G49: 0.3576 | H49: =G49*F49 -> 2.3297848e+08 | I49: =H49*D49 -> 1.635509e+08 | J49: =IF(C49="Long Options",D49*H49,0) -> 0
A51: =A49+1 -> 41 | B51: Jainam FPI | C51: Long Options | D51: 0 | E51: Derivatives | F51: 0 | G51: 1 | H51: =G51*F51 -> 0 | I51: =H51 -> 0 | J51: =IF(C51="Long Options",D51*H51,0) -> 0
A52: =A51+1 -> 42 | B52: Jainam FPI | C52: PSAR | D52: 0 | E52: Derivatives | F52: 0 | G52: 1 | H52: =G52*F52 -> 0 | I52: =H52*D52 -> 0 | J52: =IF(C52="Long Options",D52*H52,0) -> 0
A53: =A52+1 -> 43 | B53: Jainam FPI | C53: QAW Futures | D53: 0 | E53: Equity | F53: 0 | G53: 1 | H53: =G53*F53 -> 0 | I53: =H53*D53 -> 0 | J53: =IF(C53="Long Options",D53*H53,0) -> 0
A54: =A53+1 -> 44 | B54: Jainam FPI | C54: Gold Futures | D54: 0 | E54: Gold | F54: 0 | G54: 1 | H54: =G54*F54 -> 0 | I54: =H54*D54 -> 0 | J54: =IF(C54="Long Options",D54*H54,0) -> 0
A55: =A54+1 -> 45 | B55: Jainam FPI | C55: Put Protection | D55: 0 | E55: Derivatives | F55: 0 | G55: 1 | H55: =G55*F55 -> 0 | I55: =H55*D55 -> 0 | J55: =IF(C55="Long Options",D55*H55,0) -> 0

Sheet Equity Holdings
A1: paste output below:
A3: Symbol | B3: Mastersheet Tag | C3: Exchange | D3: Quantity | E3: Avg Price | F3: Broker | G3: Debt/Equity | H3: Sub Category | I3: LTP | J3: Buy Value | K3: Value as of Today | L3: PNL Amount | M3: % PNL | N3: Notes
A4: ALLETEC-SM | B4: Personal Stock Holdings Zerodha | C4: NSE | D4: 7200 | E4: 198.95 | F4: Zerodha | G4: Equity | H4: QMF | I4: 118.6 | J4: 1432440 | K4: 853919.99 | L4: -578520.01 | M4: -40.387033 | N4: Bought in RN
A5: ALPEXSOLAR-SM | B5: Personal Stock Holdings Zerodha | C5: NSE | D5: 14100 | E5: 807.0127 | F5: Zerodha | G5: Equity | H5: Discretionary Stock | I5: 759.25 | J5: 11378879 | K5: 10705425 | L5: -673454.07 | M5: -5.918457 | N5: Bought in RN
A6: BALUFORGE | B6: Personal Stock Holdings Zerodha | C6: NSE | D6: 3105 | E6: 363.4 | F6: Zerodha | G6: Equity | H6: QMF | I6: 386.2 | J6: 1128357 | K6: 1199151 | L6: 70794 | M6: 6.2740782 | N6: Bought in RN
A7: BBOX | B7: Personal Stock Holdings Zerodha | C7: NSE | D7: 4108 | E7: 475.15 | F7: Zerodha | G7: Equity | H7: QMF | I7: 447.15 | J7: 1951916.2 | K7: 1836892.2 | L7: -115024 | M7: -5.8928759 | N7: Bought in RN
A8: CAPLIPOINT | B8: Personal Stock Holdings Zerodha | C8: NSE | D8: 932 | E8: 1730.5 | F8: Zerodha | G8: Equity | H8: QMF | I8: 1504.8 | J8: 1612826 | K8: 1402473.6 | L8: -210352.4 | M8: -13.042473 | N8: Bought in RN
A9: CCAVENUE | B9: Personal Stock Holdings Zerodha | C9: NSE | D9: 250000 | E9: 19.05 | F9: Zerodha | G9: Equity | H9: Sumesh | I9: 13.4 | J9: 4762500 | K9: 3350000 | L9: -1412500 | M9: -29.658793 | N9: Bought in RN
A10: CUB | B10: Personal Stock Holdings Zerodha | C10: NSE | D10: 9337 | E10: 284.25 | F10: Zerodha | G10: Equity | H10: QMF | I10: 239.85 | J10: 2654042.2 | K10: 2239479.4 | L10: -414562.8 | M10: -15.620053 | N10: Bought in RN
A11: DEEPAKFERT | B11: Personal Stock Holdings Zerodha | C11: NSE | D11: 1383 | E11: 1156.45 | F11: Zerodha | G11: Equity | H11: QMF | I11: 909 | J11: 1599370.4 | K11: 1257147 | L11: -342223.35 | M11: -21.39738 | N11: Bought in RN
A12: DYCL | B12: Personal Stock Holdings Zerodha | C12: NSE | D12: 4791 | E12: 292.7 | F12: Zerodha | G12: Equity | H12: QMF | I12: 240.9 | J12: 1402325.7 | K12: 1154151.9 | L12: -248173.8 | M12: -17.697301 | N12: Bought in RN
A13: EXHICON | B13: Stock Holdings | C13: BSE | D13: 6750 | E13: 492.15 | F13: Zerodha | G13: Equity | H13: Sumesh | I13: 394.55 | J13: 3322037.5 | K13: 2663212 | L13: -658825 | M13: -19.709393 | N13: Bought in Mishayan
A14: FISCHER | B14: Personal Stock Holdings Zerodha | C14: NSE | D14: 50000 | E14: 40.95 | F14: Zerodha | G14: Equity | H14: Sumesh | I14: 40.5 | J14: 2047500 | K14: 2025000 | L14: -22500 | M14: -1.0989011 | N14: Bought in RN
A15: GOLDBEES | B15: Personal Stock Holdings Zerodha | C15: NSE | D15: 50800 | E15: 131.45 | F15: Zerodha | G15: Gold | H15: Goldbees | I15: 121.19 | J15: 6677660 | K15: 6156452 | L15: -521208 | M15: -7.8052491 | N15: Bought in RN
... A44: ZTECH-SM | B44: Personal Stock Holdings Zerodha | C44: NSE | D44: 3300 | E44: 572.3 | F44: Zerodha | G44: Equity | H44: QMF | I44: 507.35001 | J44: 1888590 | K44: 1674255 | L44: -214334.98 | M44: -11.348942 | N44: Bought in RN

Sheet Mutual Funds
A1: paste output below:
A3: Symbol | B3: ISIN | C3: Scheme Code | D3: Quantity | E3: Avg Price | F3: Broker | G3: Debt/Equity | H3: Mastersheet Tag | I3: Sub Category | J3: NAV | K3: Buy Value | L3: Value as of Today | M3: PNL Amount | N3: % PNL | O3: Notes
A4: ADITYA BIRLA SUN LIFE MONEY MANAGER FUND - DIRECT PLAN | B4: INF209K01UU3 | C4: 119511 | D4: 131571.1 | E4: 380.00499 | F4: Zerodha | G4: Debt | H4: Mutual Funds | I4: Liquid | J4: 392.0957 | K4: 49997673 | L4: 51588461 | M4: 1590788 | N4: 3.181724 | O4: Bought in Mishayan
A5: AXIS NIFTY500 MOMENTUM 50 INDEX FUND - DIRECT PLAN | B5: INF846KA1044 | C5: 153244 | D5: 372036.35 | E5: 10.8774 | F5: Zerodha | G5: Equity | H5: Personal Mutual Funds Zerodha | I5: Momentum | J5: 9.4931 | K5: 4046788.2 | L5: 3531778.3 | M5: -515009.92 | N5: -12.726387 | O5: Bought in RN
A6: ICICI PRUDENTIAL NIFTY 100 LOW VOLATILITY 30 ETF FOF - DIRECT PLAN | B6: INF109KC1P81 | C6: 148822 | D6: 1699682.6 | E6: 18.13717 | F6: Zerodha | G6: Equity | H6: Personal Mutual Funds Zerodha | I6: Low Vol | J6: 16.9348 | K6: 30827431 | L6: 28783784 | M6: -2043647.3 | N6: -6.6293143 | O6: Bought in RN
A7: KOTAK NIFTY 200 MOMENTUM 30 INDEX FUND - DIRECT PLAN | B7: INF174KA1OB1 | C7: 151781 | D7: 2961798 | E7: 14.93707 | F7: Zerodha | G7: Equity | H7: Personal Mutual Funds Zerodha | I7: Momentum | J7: 12.909 | K7: 44240584 | L7: 38233850 | M7: -6006733.6 | N7: -13.577429 | O7: Bought in RN
A8: LIC MF LIQUID FUND - DIRECT PLAN | B8: INF767K01DN1 | C8: 120249 | D8: 8191.813 | E8: 4882.6793 | F8: Zerodha | G8: Debt | H8: Mutual Funds | I8: Liquid | J8: 5000.4251 | K8: 39997995 | L8: 40962547 | M8: 964551.9 | N8: 2.4115006 | O8: Bought in Mishayan
A9: MOTILAL OSWAL NIFTY 500 MOMENTUM 50 INDEX FUND - DIRECT PLAN | B9: INF247L01DL6 | C9: 152875 | D9: 1136231.3 | E9: 8.2241 | F9: Zerodha | G9: Equity | H9: Personal Mutual Funds Zerodha | I9: Momentum | J9: 7.1238 | K9: 9344479.6 | L9: 8094284.3 | M9: -1250195.3 | N9: -13.378972 | O9: Bought in RN
A10: NIPPON INDIA MONEY MANAGER FUND - DIRECT PLAN | B10: INF204K01ZP3 | C10: 118719 | D10: 4585.99 | E10: 4360.89 | F10: Zerodha | G10: Debt | H10: Mutual Funds | I10: Liquid | J10: 4399.226 | K10: 19998998 | L10: 20174806 | M10: 175808.51 | N10: 0.87908661 | O10: Bought in Mishayan
A11: PARAG PARIKH ELSS TAX SAVER FUND - DIRECT PLAN | B11: INF879O01100 | C11: 147481 | D11: 7843.114 | E11: 34.7816 | F11: Zerodha | G11: Equity | H11: Personal Mutual Funds Zerodha | I11: Large Cap | J11: 30.025 | K11: 272796.05 | L11: 235489.5 | M11: -37306.556 | N11: -13.675622 | O11: Bought in RN
A12: QUANT LARGE CAP FUND - DIRECT PLAN | B12: INF966L01AT0 | C12: 150440 | D12: 1250128.3 | E12: 15.2113 | F12: Zerodha | G12: Equity | H12: Personal Mutual Funds Zerodha | I12: Large Cap | J12: 13.7623 | K12: 19016077 | L12: 17204641 | M12: -1811436 | N12: -9.525813 | O12: Bought in RN
A13: TATA NIFTY MIDCAP 150 MOMENTUM 50 INDEX FUND - DIRECT PLAN | B13: INF277KA1612 | C13: 150738 | D13: 2367424.1 | E13: 16.39663 | F13: Zerodha | G13: Equity | H13: Personal Mutual Funds Zerodha | I13: Momentum | J13: 16.0216 | K13: 38817778 | L13: 37929923 | M13: -887855.08 | N13: -2.2872383 | O13: Bought in RN

Sheet Mishayan STCG
B3: Capital Gains in Mishayan
B5: Sr. No. | C5: Symbol | D5: Current Value | E5: Total Profit | F5: LTCG | G5: STCG | H5: Date till when we can book STCG | I5: Equity/Debt
B6: 1 | C6: HDFC NIFTY 200 MOMENTUM 30 INDEX FUND | D6: 4132903.6 | E6: 384713.88 | G6: 384713.88 | H6: 46068 | I6: Equity
B7: =B6+1 -> 2 | C7: EDELWEISS NIFTY MIDCAP 150 MOMENTUM 50 INDEX FUND - DIRECT PLAN | D7: 7313587 | E7: 648203 | F7: -54676 | G7: 702879 | H7: 46068 | I7: Equity
B8: =B7+1 -> 3 | C8: ADITYA BIRLA SUN LIFE MONEY MANAGER FUND - DIRECT PLAN | D8: 31038878 | E8: 1040266 | G8: 1040266 | H8: 46168 | I8: Debt
B9: =B8+1 -> 4 | C9: LIC MF LIQUID FUND - DIRECT PLAN | D9: 40416545 | E9: 418550 | G9: 418550 | H9: 46317 | I9: Debt
C10: Total | D10: =SUM(D6:D9) -> 82901914 | E10: =SUM(E6:E9) -> 2491732.9 | F10: =SUM(F6:F9) -> -54676 | G10: =SUM(G6:G9) -> 2546408.9

Sheet Fund Returns
A1: Phase 2:
A2: to be done later
A4: paste mastersheet
A5: look at live nav numbers
A6: create summary table

Sheet Fund Arrangement
C2: Rishabh | D2: Mishayan | E2: Total
B3: Capital Needed | C3: 12000000 | D3: =E3-C3 -> 108000000 | E3: 120000000 | H3: 15 cr in mishayan | M3: Min: 15 cr needed
A8: 1. | B8: LIC MF LIQUID FUND | C8: 3927525.1 | H8: LIC MF LIQUID FUND | I8: 3927525.1 | M8: 1. Sell LIC Liquid MF in RN and give loan to Mishayan | N8: 3937411.7
M9: 2. GRD | N9: 5200000
A10: 2. | B10: Excess cash in account: | C10: ='Cash and Margin - old'!R7 -> 1.4571648e+08 | H10: dd margin and excess cash | I10: ='Cash and Margin - old'!T22 -> 0 | M10: 3. Swan Capital | N10: 5500000 | O10: first confirm with karan if we take in swan or not
B11: reverse dmf loan of this value from mishayan to RN. Sell that MF in RN | M11: 4. HDFC Bank RN | N11: 6000000
M12: 5. HDFC Bank Mishayan | N12: 6000000
A13: 3. | B13: GRD | C13: =5200000 -> 5200000 | H13: GRD | I13: =5200000 -> 5200000 | M13: 6. OD | N13: 29700000
M14: 7. Excess cash in RN Zerodha | N14: 0
A15: 4. | B15: Swan Capital | C15: 5799552 | H15: Swan Capital | I15: 5799552 | M15: 8. Excess cash in Mishayan Zerodha | N15: =SUM(N16:N17) -> 1.6999251e+08
M16: excess cash | N16: ='Cash and Margin - old'!R7 -> 1.4571648e+08
A17: 5. | B17: HDFC Bank RN | C17: 5632941 | H17: HDFC Bank RN | I17: ='Networth Inputs - old'!E14 -> 1550293 | M17: dd margin | N17: ='Cash and Margin - old'!P10*2 -> 24276037
H18: mishayan | I18: ='Networth Inputs - old'!E15 -> 4287189
A19: 6. | B19: Zerodha Cash | C19: ='Networth Inputs - old'!E21-(25000000-C20) -> 15463057 | M19: Total available | N19: =SUM(N8:N15) -> 2.2632993e+08
B20: Sumesh stock value | C20: =SUMIFS('Equity Holdings'!$J$11:$J$49,'Equity Holdings'!$H$11:$H$49,'Equity Holdings'!$H$16) -> 40448205 | H20: od | I20: =C22 -> 48398458
M21: in this sumesh cannot buy any stock in this time frame
A22: 7. | B22: ICICI Bank OD | C22: ='Networth Inputs - old'!E36 -> 48398458 | H22: rn zerodha | I22: =C19 -> 15463057
H24: total | I24: =SUM(I8:I22) -> 84626074
B25: Total Available | C25: =C8+C10+C13+C15+C17+C19+C22 -> 2.3013801e+08 | M25: dmf inrn | N25: 39 lacs
B26: Balance | C26: =C25-E3 -> 1.1013801e+08 | H26: as of now use 10 cr from here and borrow 5 cr | M26: cash in bank (rn+mishayan) | N26: 50 lacs
M27: od | N27: 4.83 cr
B28: 3 cr we can adjust with hedging in mishayan | M28: cash in mishayan zerodha | N28: 11 cr
M29: dd margin | N29: 1 cr | O29: but sell full lc
M30: dd lc | N30: 75 lacs
N32: =0.39+0.5+4.83+11+1+0.75 -> 18.47 | O32: 18 cr

Sheet Strategy Allocation Old
L1: 1. System Should always run
L2: 2. System should not shut if dd is under 10%
G3: =SUM(G5:G302) -> 24471886 | L3: 3. Maintain enough deposit to run the system
A4: Sr.No. | B4: Account | C4: Strategy Name | D4: Position Sizing | E4: Exposure | F4: Net Exposure | G4: Long options premium | H4: Deposit | I4: Lev | L4: 4. Should not be running last minute for deposit
A5: 1 | B5: Mishayan Zerodha Client Account | C5: Long Options | D5: 0.015 | E5: ='Cash and Margin - old'!C22 -> 7.2828112e+08 | F5: =E5 -> 7.2828112e+08 | G5: =+IF(C5=$C$5,D5*F5,"") -> 10924217 | L5: 5. Don’t take payout if scaling up and 10% is not maintained
A6: =A5+1 -> 2 | B6: Mishayan Zerodha Client Account | C6: PSAR | D6: 2.12 | E6: ='Cash and Margin - old'!C22 -> 7.2828112e+08 | F6: =E6*D6 -> 1.543956e+09 | G6: =+IF(C6=$C$5,D6*F6,"")
A7: =A6+1 -> 3 | B7: Mishayan Zerodha Client Account | C7: Gold | D7: 1 | E7: ='Cash and Margin - old'!A27 -> 304237500 | F7: =E7 -> 304237500 | G7: =+IF(C7=$C$5,D7*F7,"")
A8: =A7+1 -> 4 | B8: Mishayan Zerodha Client Account | C8: Put Protection | D8: 1 | E8: ='Cash and Margin - old'!A33 -> 4.1095882e+08 | F8: =E8 -> 4.1095882e+08 | G8: =+IF(C8=$C$5,D8*F8,"")
A9: =A8+1 -> 5 | B9: Mishayan Zerodha Client Account | C9: Stock Futures | D9: 1 | E9: 0 | F9: =E9 -> 0
A10: =A9+1 -> 6 | B10: SRE | C10: Long Options | D10: 0.015 | E10: =194700000*60% -> 116820000 | F10: =E10 -> 116820000 | G10: =+IF(C10=$C$5,D10*F10,"") -> 1752300
A11: =A10+1 -> 7 | B11: SRE | C11: PSAR | D11: 2 | E11: =194700000*60% -> 116820000 | F11: =D11*E11 -> 233640000 | G11: =+IF(C11=$C$5,D11*F11,"") | H11: =9372839+2500000 -> 11872839 | I11: =E11/H11 -> 9.8392642
A12: =A11+1 -> 8 | B12: Aurus Alpha | C12: Long Options | D12: 0.025 | E12: =(348700000+349000000)*35.75% -> 249427750 | F12: =E12 -> 249427750 | G12: =+IF(C12=$C$5,D12*F12,"") -> 6235693.8
A13: =A12+1 -> 9 | B13: Aurus Alpha | C13: PSAR | D13: 3.34 | E13: =(348700000+349000000)*35.75% -> 249427750 | F13: =D13*E13 -> 833088685 | G13: =+IF(C13=$C$5,D13*F13,"") | H13: =VLOOKUP("Aurus Alpha Deposit",'Networth Inputs - old'!$C$4:$E$74,3,FALSE)+VLOOKUP("Aurus Alpha Profit",'Networth Inputs - old'!$C$4:$E$74,3,FALSE) -> 66384401 | I13: 7
A14: =A13+1 -> 10 | B14: Marwadi | C14: Long Options | D14: 0.015 | E14: =1780000000*12.77% -> 227306000 | F14: =+E14 -> 227306000 | G14: =+IF(C14=$C$5,D14*F14,"") -> 3409590 | L14: PROP SIDE
A15: =A14+1 -> 11 | B15: Marwadi | C15: PSAR | D15: 3 | E15: =1780000000*12.77% -> 227306000 | F15: =D15*E15 -> 681918000 | G15: =+IF(C15=$C$5,D15*F15,"") | H15: =VLOOKUP("Marwadi Deposit",'Networth Inputs - old'!$C$4:$E$74,3,FALSE) -> 10200000 | I15: 10 | L15: 1. Payout from marwadi and marwadi accounts
A16: =A15+1 -> 12 | B16: Marwadi | C16: Gold Futures | D16: 1 | E16: =1780000000*12.77%*40% -> 90922400 | F16: =D16*E16 -> 90922400 | H16: =VLOOKUP("Marwadi Deposit",'Networth Inputs - old'!$C$4:$E$74,3,FALSE) -> 10200000 | I16: 10
A17: =A16+1 -> 13 | B17: Marwadi | C17: QAW Futures | D17: 1 | E17: =1780000000*12.77%*40% -> 90922400 | F17: =D17*E17 -> 90922400 | H17: =VLOOKUP("Marwadi Deposit",'Networth Inputs - old'!$C$4:$E$74,3,FALSE) -> 10200000 | I17: 10
A18: =A17+1 -> 14 | B18: Marwadi FPI | C18: Long Options | D18: 0.015 | E18: =1420000000*18%*35% -> 89460000 | F18: =+E18 -> 89460000 | G18: =+IF(C18=$C$5,D18*F18,"") -> 1341900 | L18: payout in gift city
A19: =A18+1 -> 15 | B19: Marwadi FPI | C19: PSAR | D19: 3 | E19: =1420000000*18%*35% -> 89460000 | F19: =D19*E19 -> 268380000 | G19: =+IF(C19=$C$5,D19*F19,"") | H19: =VLOOKUP("Marwadi FPI Deposit (FD)",'Networth Inputs - old'!$C$4:$E$74,3,FALSE) -> 2625000 | I19: =E19/H19 -> 34.08 | L19: 2. affluence accounts
A20: =A19+1 -> 16 | B20: Marwadi FPI | C20: QAW Futures | D20: 1 | E20: =1420000000*18%*35%*60% -> 53676000 | F20: =D20*E20 -> 53676000
A21: =A20+1 -> 17 | B21: Affluence Prop | C21: Long Options | D21: 0.015 | E21: =248800000*30%*35% -> 26124000 | F21: =+E21 -> 26124000 | G21: =+IF(C21=$C$5,D21*F21,"") -> 391860
A22: =A21+1 -> 18 | B22: Affluence Prop | C22: PSAR | D22: 3 | E22: =248800000*30%*35% -> 26124000 | F22: =D22*E22 -> 78372000 | G22: =+IF(C22=$C$5,D22*F22,"")
A23: =A22+1 -> 19 | B23: Affluence Prop | C23: QAW Futures | D23: 1 | E23: =248800000*30%*35%*60% -> 15674400 | F23: =D23*E23 -> 15674400 | G23: =+IF(C23=$C$5,D23*F23,"")
A24: =A23+1 -> 20 | B24: Affluence Prop | C24: Gold Futures | D24: 1 | E24: =248800000*30%*35%*40% -> 10449600 | F24: =D24*E24 -> 10449600 | G24: =+IF(C24=$C$5,D24*F24,"")
A25: =A24+1 -> 21 | B25: Ashika | C25: Long Options | D25: 0.015 | E25: =100000000*20%*35% -> 7000000 | F25: =D25*E25 -> 105000 | G25: =+IF(C25=$C$5,D25*F25,"") -> 1575
A26: =A25+1 -> 22 | B26: Ashika | C26: PSAR | D26: 2 | E26: =100000000*20%*35% -> 7000000 | F26: =D26*E26 -> 14000000 | G26: =+IF(C26=$C$5,D26*F26,"")
A27: =A26+1 -> 23 | G27: =+IF(C27=$C$5,D27*F27,"") | L27: get lev on our book and psar 3.25 cr
A28: =A27+1 -> 24 | B28: SRE | C28: QAW Futures | D28: 1 | E28: =194700000*60%*60% -> 70092000 | F28: =D28*E28 -> 70092000 | G28: =+IF(C28=$C$5,D28*F28,"")
A29: =A28+1 -> 25 | B29: SRE | C29: Gold Futures | D29: 1 | E29: =180000000*60%*0% -> 0 | F29: =D29*E29 -> 0 | G29: =+IF(C29=$C$5,D29*F29,"")
A30: =A29+1 -> 26 | B30: Affluence High Risk | C30: Long Options | D30: 0.02 | E30: =197500000*30%*35% -> 20737500 | F30: =+E30 -> 20737500 | G30: =+IF(C30=$C$5,D30*F30,"") -> 414750
A31: =A30+1 -> 27 | B31: Affluence High Risk | C31: PSAR | D31: 6 | E31: =197500000*30%*35% -> 20737500 | F31: =D31*E31 -> 124425000
A32: =A31+1 -> 28 | B32: Aurus Alpha | C32: QAW Futures | D32: 1.17 | E32: =(348700000+349000000)*35.75%*60% -> 149656650 | F32: =D32*E32 -> 1.7509828e+08 | G32: =+IF(C32=$C$5,D32*F32,"") | I32: 7 | K32: =((346700000+346900000)*35.75%)*70.2% -> 1.7406932e+08
A33: =A32+1 -> 29 | B33: Aurus Alpha | C33: Gold Futures | D33: 1.17 | E33: =(348700000+349000000)*35.75%*40% -> 99771100 | F33: =D33*E33 -> 116732187 | G33: =+IF(C33=$C$5,D33*F33,"") | I33: 7 | K33: =((346700000+346900000)*35.75%)*46.8% -> 116046216
A34: =A33+1 -> 30 | B34: Marwadi | C34: Put Protection | D34: 1 | E34: =E17+E38 -> 129232400 | F34: =D34*E34 -> 129232400 | G34: =+IF(C34=$C$5,D34*F34,"")
A35: =A34+1 -> 31 | B35: Marwadi FPI | C35: Put Protection | D35: 1 | E35: =E20 -> 53676000 | F35: =D35*E35 -> 53676000 | G35: =+IF(C35=$C$5,D35*F35,"")
A36: =A35+1 -> 32 | B36: Affluence Prop | C36: Put Protection | D36: 1 | E36: =E23+E39 -> 18824400 | F36: =D36*E36 -> 18824400 | G36: =+IF(C36=$C$5,D36*F36,"")
A37: =A36+1 -> 33 | B37: SRE | C37: Put Protection | D37: 1 | E37: =E28 -> 70092000 | F37: =D37*E37 -> 70092000 | G37: =+IF(C37=$C$5,D37*F37,"")
A38: =A37+1 -> 34 | B38: Marwadi | C38: Stock Futures | D38: 1 | E38: =10*30000000*12.77% -> 38310000 | F38: =D38*E38 -> 38310000 | G38: =+IF(C38=$C$5,D38*F38,"") | H38: =VLOOKUP("Marwadi Deposit",'Networth Inputs - old'!$C$4:$E$74,3,FALSE) -> 10200000 | I38: 10
A39: =A38+1 -> 35 | B39: Affluence Prop | C39: Stock Futures | D39: 1 | E39: =30000000*30%*35% -> 3150000 | F39: =D39*E39 -> 3150000 | G39: =+IF(C39=$C$5,D39*F39,"")
A40: =A39+1 -> 36 | B40: Mishayan Zerodha Client Account | C40: Gold PRCS | D40: 1 | E40: 0 | F40: =E40*D40 -> 0 | G40: =+IF(C40=$C$5,D40*F40,"")
A41: =A40+1 -> 37 | B41: Aurus Alpha | C41: Gold PRCS | D41: 1 | E41: 0 | F41: =E41*D41 -> 0 | G41: =+IF(C41=$C$5,D41*F41,"")
A42: =A41+1 -> 38 | B42: Marwadi | C42: Gold PRCS | D42: 1 | E42: 0 | F42: =E42*D42 -> 0 | G42: =+IF(C42=$C$5,D42*F42,"")
A43: =A42+1 -> 39 | B43: Aurus Alpha | C43: Put Protection | D43: 1 | E43: =E32 -> 149656650 | F43: =E43*D43 -> 149656650
A44: =A43+1 -> 40 | B44: Marwadi FPI | C44: Gold Futures | D44: 1 | E44: =1480000000*18%*35%*40% -> 37296000 | F44: =E44*D44 -> 37296000

Sheet Networth Inputs - old
A1: Liquidity: | J1: Debt: | P1: Networth: | T1: S.no | U1: Notes for Action: 12.12.2025
T2: 1 | U2: Marwari Pauout for FPI and for India prop Figure
A3: Sr. No. | B3: Category | C3: Particulars | D3: Equity / Debt | E3: Value | F3: Mishayan / Rishabh | G3: Data as of | J3: Sr. No. | K3: Category | L3: Particulars | M3: Value | P3: Particulars | Q3: Value | T3: 2 | U3: Affluence Payout
A4: 1 | B4: Other Investments | C4: Sushila Nahar Equity MF | D4: Equity | E4: 15368350 | F4: Rishabh Nahar | J4: 1 | K4: debt | L4: Fancy Nahar | M4: =E8 -> 0 | P4: Liquidity | Q4: =SUM(E4:E108) -> 8.9887254e+08 | T4: 3 | U4: Jainam accounts close
A5: =A4+1 -> 2 | B5: Other Investments | C5: Yogita Agrawal PMS | D5: Equity | E5: 40685877 | F5: Rishabh Nahar | J5: =J4+1 -> 2 | K5: debt | L5: Deepak Nahar | M5: =E9 -> 0 | P5: Less: Debt | Q5: =SUM(M4:M108) -> 67500000 | T5: 4 | U5: YG QAW Start and scale account
A6: =A5+1 -> 3 | J6: =J5+1 -> 3 | K6: debt | L6: ICICI Bank OD | M6: 65000000 | P6: Networth | Q6: =Q4-Q5 -> 8.3137254e+08 | T6: 5 | U6: Give Deposit to Marwari
A7: =A6+1 -> 4 | B7: Other Investments | C7: Loan to Vihaan | D7: Debt | E7: 3000000 | F7: Rishabh Nahar | J7: =J6+1 -> 4 | K7: debt | L7: Sumesh | M7: 2500000 | Q7: =Q6*2 -> 1.6627451e+09 | T7: 6 | U7: Update YG Profits Number and confirm with him
A8: =A7+1 -> 5 | T8: 7 | U8: Breakup of capital in the company vs in Personal
A9: =A8+1 -> 6 | T9: 8 | U9: Total Exposure wise calculation in a different sheet
A10: =A9+1 -> 7 | B10: Prop Deposits | C10: Aurus Alpha Deposit | D10: Debt | E10: 31500000 | F10: Mishayan | T10: 9 | U10: Minimize capitlal in the company, figure a method to take more on personal books
A11: =A10+1 -> 8 | B11: Prop Deposits | C11: Aurus Alpha Profit | D11: Debt | E11: 34884401 | F11: Rishabh Nahar | T11: 10 | U11: Idea is to predict wheree money needs to be moved at least on the underlying space overall
A12: =A11+1 -> 9 | B12: Other Investments | C12: PMS QFH Strategy | D12: Equity | E12: 6092676 | F12: Rishabh Nahar | T12: 11 | U12: Try and keep max exposure on our books itself, so that profits can be compounded whenever needed.
A13: =A12+1 -> 10 | B13: Other Investments | C13: Swan Capital | D13: Debt | E13: 5881036 | F13: Rishabh Nahar | T13: 12 | U13: Start Using the OD for exposure on our books
A14: =A13+1 -> 11 | B14: FD | C14: HDFC Bank RN | D14: Cash | E14: 1550293 | F14: Rishabh Nahar | T14: 13 | U14: 19-02-2025 Shift Hdfc and edelweiss momentum (sell in mishayan and buy in RN)
A15: =A14+1 -> 12 | B15: FD | C15: HDFC Bank Mishayan | D15: Cash | E15: 4287189 | F15: Mishayan | T15: 14 | U15: Check for jainam deposit math and update in this sheet
A16: =A15+1 -> 13 | B16: Other Investments | C16: SRE | D16: Debt | E16: =2500000+16585388+(21512053-2800000)*60% -> 30312620 | F16: Rishabh Nahar
A17: =A16+1 -> 14 | B17: Other Investments | C17: Interest Hand | D17: Debt | E17: 0 | F17: Rishabh Nahar
A18: =A17+1 -> 15 | B18: FD | C18: FD | D18: Debt | E18: =10000000+3150000+10350000 -> 23500000 | F18: Rishabh Nahar
A19: =A18+1 -> 16 | B19: Client Account | C19: Zerodha Broking RN: EQ Holdings | D19: Equity | E19: =SUMIFS('Equity Holdings'!$K$9:$K$126,'Equity Holdings'!$B$9:$B$126,"Personal Stock Holdings Zerodha",'Equity Holdings'!$G$9:$G$126,"Equity")+SUMIFS('Equity Holdings'!$K$9:$K$126,'Equity Holdings'!$B$9:$B$126,"Personal Stock Holdings Zerodha",'Equity Holdings'!$G$9:$G$126,"Gold") -> 86524104 | F19: Rishabh Nahar
A20: =A19+1 -> 17 | B20: Client Account | C20: Zerodha Broking RN: EQ Mutual Funds | D20: Equity | E20: =SUMIFS('Mutual Funds'!$L$24:$L$73,'Mutual Funds'!$G$24:$G$73,"Equity",'Mutual Funds'!$I$24:$I$73,"Personal Mutual Funds Zerodha") -> 0 | F20: Rishabh Nahar
A21: =A20+1 -> 18 | B21: Client Account | C21: Zerodha Broking RN: Cash | D21: Cash | E21: 14852 | F21: Rishabh Nahar
A22: =A21+1 -> 19 | B22: Client Account | C22: Zerodha Broking RN: Debt Mutual Funds | D22: Debt | E22: =SUMIFS('Mutual Funds'!$L$24:$L$73,'Mutual Funds'!$G$24:$G$73,"Debt",'Mutual Funds'!$I$24:$I$73,"Personal Mutual Funds Zerodha") -> 0 | F22: Rishabh Nahar
A24: =A23+1 -> 1 | B24: Client Account | C24: Zerodha Broking Mishayan: EQ Holdings | D24: Equity | E24: =24489025.54-E27 -> 24489026 | F24: Mishayan | I24: =SUMIFS('Equity Holdings'!$K$9:$K$126,'Equity Holdings'!$B$9:$B$126,"Stock Holdings",'Equity Holdings'!$G$9:$G$126,"Equity")+SUMIFS('Equity Holdings'!$K$9:$K$126,'Equity Holdings'!$B$9:$B$126,"Stock Holdings",'Equity Holdings'!$G$9:$G$126,"Gold") -> 2663212 | P24: Pending Liquidity
A25: =A24+1 -> 2 | B25: Client Account | C25: Zerodha Broking Mishayan: EQ Mutual Fund | D25: Equity | E25: =299945688.54-E26 -> 2.9994569e+08 | F25: Mishayan | I25: =SUMIFS('Mutual Funds'!$L$24:$L$73,'Mutual Funds'!$G$24:$G$73,"Equity",'Mutual Funds'!$I$24:$I$73,"Mutual Funds") -> 0 | P25: World One 11N2
A26: =A25+1 -> 3 | B26: Client Account | C26: Zerodha Broking Mishayan: Debt Mutual Fund | D26: Debt | E26: =SUMIFS('Mutual Funds'!$L$24:$L$73,'Mutual Funds'!$G$24:$G$73,"Debt",'Mutual Funds'!$I$24:$I$73,"Mutual Funds") -> 0 | F26: Mishayan | I26: =SUMIFS('Mutual Funds'!$L$24:$L$73,'Mutual Funds'!$G$24:$G$73,"Debt",'Mutual Funds'!$I$24:$I$73,"Mutual Funds") -> 0 | P26: Gold | Q26: 80000000
A27: =A26+1 -> 4 | B27: Client Account | C27: Zerodha Broking Mishayan: Liquidbees/ Liquidcase | D27: Debt | E27: =SUMIFS('Equity Holdings'!$K$11:$K$82,'Equity Holdings'!$G$11:$G$82,"Debt",'Equity Holdings'!$B$11:$B$82,"Stock Holdings") -> 0 | F27: Mishayan | I27: =SUMIFS('Equity Holdings'!$K$11:$K$82,'Equity Holdings'!$G$11:$G$82,"Debt",'Equity Holdings'!$B$11:$B$82,"Stock Holdings") -> 0
A28: =A27+1 -> 5 | B28: Client Account | C28: Zerodha Broking Mishayan: Cash | D28: Cash | E28: =157795980-6252411 -> 151543569 | F28: Mishayan | I28: =185416310.27-127623 -> 1.8528869e+08 | Q28: =E27+Q25+Q26 -> 80000000
A30: =A29+1 -> 1 | B30: Prop Deposits | C30: Marwadi Deposit | D30: Debt | E30: 10200000 | F30: Rishabh Nahar
A31: =A30+1 -> 2 | B31: Prop Deposits | C31: Marwadi Profits | D31: Debt | E31: 34479751 | F31: Rishabh Nahar
A32: =A31+1 -> 3
A33: =A32+1 -> 4 | B33: Prop Deposits | C33: Marwadi FPI Deposit (FD) | D33: Debt | E33: 2625000 | F33: Rishabh Nahar
A34: =A33+1 -> 5 | B34: Prop Deposits | C34: Affluence | D34: Debt | E34: =3780911-929588+(33958675-1108325-6756000)*30%*35% -> 5591229.8 | F34: Rishabh Nahar
A35: =A34+1 -> 6 | B35: Prop Deposits | C35: Affluence High Risk | D35: Debt | E35: =746770.22+1108983.82+3253254+(186766)*30%*35% -> 5128618.5 | F35: Rishabh Nahar
A36: =A35+1 -> 7 | B36: FD | C36: ICICI Bank OD | D36: Debt | E36: 48398458 | F36: Rishabh Nahar
A37: =A36+1 -> 8 | B37: Prop Deposits | C37: Jainam Allocation Deposit | D37: Debt | E37: 0 | F37: Deepak Nahar | I37: 25 lacs gone from deepak nahar
A38: =A37+1 -> 9 | B38: FD | C38: HDFC Bank FD | D38: Debt | E38: 1000000 | F38: Mishayan
A39: =A38+1 -> 10 | B39: Prop Deposits | C39: Marwadi FPI Profits | D39: Debt | E39: 15169806 | F39: Rishabh Nahar
A40: =A39+1 -> 11 | B40: FD | C40: Nimai FD | D40: Debt | E40: 0 | F40: Rishabh Nahar
A41: =A40+1 -> 12 | B41: FD | C41: Arvind FD | D41: Debt | E41: 700000 | F41: Rishabh Nahar
A42: =A41+1 -> 13 | B42: Other Investments | C42: Sushila Nahar HDFC | D42: Cash | E42: 0 | F42: Rishabh Nahar
A43: =A42+1 -> 14 | B43: Other Investments | C43: Sushila Nahar Zerodha | D43: Equity | E43: 13500000 | F43: Rishabh Nahar
A44: =A43+1 -> 15 | B44: FD | C44: Sumesh FD | D44: Debt | E44: 2500000 | F44: Rishabh Nahar
A45: =A44+1 -> 16

Sheet Cash and Margin - old
A1: Total Exposure in Mishayan for Long & Psar: | F1: Inputs: | L1: Cash and Non Cash Component
S2: =Q5/C22 -> 0.20808389
A3: Sr. No. | B3: Particulars | C3: Value | F3: Sr. No. | G3: Particulars | H3: Input | L3: Sr. No. | M3: System | N3: Cash Component (Liquid Funds) | O3: Non Cash Component | P3: Liquidbees | Q3: Cash | R3: Total
A4: 1 | B4: ='Networth Inputs - old'!C4 -> Sushila Nahar Equity MF | C4: ='Networth Inputs - old'!E4 -> 15368350 | F4: 1 | G4: Long Options PS | H4: 0.015
A5: =A4+1 -> 2 | B5: ='Networth Inputs - old'!C5 -> Yogita Agrawal PMS | C5: ='Networth Inputs - old'!E5 -> 40685877 | F5: =F4+1 -> 2 | G5: PSAR Multiplier | H5: 2.1 | L5: 1 | M5: Available on Zerodha | N5: =159472858-0.94*P5 -> 159472858 | O5: 129260830 | P5: =VLOOKUP("Zerodha Broking Mishayan: Liquidbees/ Liquidcase",'Networth Inputs - old'!$C$4:$E$114,3,FALSE) -> 0 | Q5: =VLOOKUP("Zerodha Broking Mishayan: Cash",'Networth Inputs - old'!$C$4:$E$114,3,FALSE) -> 151543569 | R5: =SUM(N5:Q5) -> 440277257 | T5: Current Cash % | U5: =Q5/C22 -> 0.20808389
A6: =A5+1 -> 3 | B6: ='Networth Inputs - old'!C38 -> HDFC Bank FD | C6: ='Networth Inputs - old'!E38 -> 1000000 | F6: =F5+1 -> 3 | G6: Psar Leverage | H6: 8 | L6: =L5+1 -> 2 | M6: Total Required | N6: =SUM(N9:N16) -> 1.2094002e+08 | O6: =SUM(O9:O16) -> 1.2094002e+08 | P6: =SUM(P9:P16) -> 12138019 | Q6: =SUM(Q9:Q16) -> 40542719 | R6: =SUM(R9:R16) -> 2.9456078e+08
A7: =A6+1 -> 4 | B7: ='Networth Inputs - old'!C7 -> Loan to Vihaan | C7: ='Networth Inputs - old'!E7 -> 3000000 | F7: =F6+1 -> 4 | G7: Cash Drawdown Margin | H7: =5%*2/3 -> 0.033333333 | L7: =L6+1 -> 3 | M7: Margin Excess/Shortfall | N7: =N5-N6 -> 38532836 | O7: =O5-O6 -> 8320808.3 | P7: =P5-P6 -> -12138019 | Q7: =Q5-Q6 -> 1.1100085e+08 | R7: =SUM(N7:Q7) -> 1.4571648e+08
A8: =A7+1 -> 5 | B8: ='Networth Inputs - old'!C8 -> 0 | C8: 0 | F8: =F7+1 -> 5 | G8: Liquidbees Drawdown Margin | H8: =5%*1/3 -> 0.016666667
A9: =A8+1 -> 6 | B9: ='Networth Inputs - old'!C9 -> 0 | C9: 0 | F9: =F8+1 -> 6 | G9: DMA Cash Requirement | H9: 0.013 | L9: 1 | M9: Cash Drawdown Margin | Q9: =H7*C22 -> 24276037 | R9: =SUM(N9:Q9) -> 24276037 | S9: =Q9/$C$22 -> 0.033333333
A10: =A9+1 -> 7 | B10: ='Networth Inputs - old'!C12 -> PMS QFH Strategy | C10: ='Networth Inputs - old'!E12 -> 6092676 | F10: =F9+1 -> 7 | G10: Gold Fut + PRCS Leverage | H10: 6 | L10: =L9+1 -> 2 | M10: Liquidbees Drawdown Margin | P10: =H8*C22 -> 12138019 | R10: =SUM(N10:Q10) -> 12138019 | S10: =P10/$C$22 -> 0.016666667
A11: =A10+1 -> 8 | B11: ='Networth Inputs - old'!C14 -> HDFC Bank RN | C11: ='Networth Inputs - old'!E14 -> 1550293 | F11: =F10+1 -> 8 | G11: Gold PRCS Cash | H11: 0
A12: =A11+1 -> 9 | B12: ='Networth Inputs - old'!C15 -> HDFC Bank Mishayan | C12: ='Networth Inputs - old'!E15 -> 4287189 | F12: =F11+1 -> 9 | G12: Stock Futures Leverage | H12: 0 | I12: 2.5 | L12: 1 | M12: Long Options | Q12: =H4*C22 -> 10924217 | R12: =SUM(N12:Q12) -> 10924217 | S12: =Q12/$C$22 -> 0.015
A13: =A12+1 -> 10 | B13: ='Networth Inputs - old'!C17 -> Interest Hand | C13: ='Networth Inputs - old'!E17 -> 0 | F13: =F12+1 -> 10 | L13: =L12+1 -> 2 | M13: PSAR | N13: =$C$22*$H$5/$H$6/2 -> 95586897 | O13: =$C$22*$H$5/$H$6/2 -> 95586897 | R13: =SUM(N13:Q13) -> 1.9117379e+08
A14: =A13+1 -> 11 | B14: ='Networth Inputs - old'!C18 -> FD | C14: ='Networth Inputs - old'!E18 -> 23500000 | L14: =L13+1 -> 3 | M14: DMA | Q14: =$H$9*A33 -> 5342464.6 | R14: =SUM(N14:Q14) -> 5342464.6 | S14: =Q14/$C$22 -> 0.0073357176
A15: =A14+1 -> 12 | B15: Zerodha Broking RN: | C15: =SUM('Networth Inputs - old'!E19:E23) -> 86538956 | L15: =L14+1 -> 4 | M15: Gold Fut + PRCS | N15: =$A$27/$H$10/2 -> 25353125 | O15: =$A$27/$H$10/2 -> 25353125 | Q15: =H11*A27 -> 0 | R15: =SUM(N15:Q15) -> 50706250 | S15: =Q15/$C$22 -> 0
A16: =A15+1 -> 13 | B16: Zerodha Broking Mishayan: | C16: =SUM('Networth Inputs - old'!E24:E29) -> 4.7597828e+08 | L16: 6 | M16: Stock Futures | S16: =Q16/$C$22 -> 0
A17: =A16+1 -> 14 | B17: ='Networth Inputs - old'!C32 -> 0 | C17: ='Networth Inputs - old'!E32 -> 0 | F17: Note: | G17: Cash + DD Margin for 3x psar is 15%
A18: =A17+1 -> 15 | B18: ='Networth Inputs - old'!C36 -> ICICI Bank OD | C18: ='Networth Inputs - old'!E36 -> 48398458 | G18: Cash + DD Margin for 2x psar is 5% | M18: required in mishayan | N18: =N6/0.9 -> 1.343778e+08 | O18: =O6/0.8 -> 1.5117503e+08 | P18: =P6 -> 12138019 | Q18: =Q6 -> 40542719 | R18: =SUM(N18:Q18) -> 3.3823357e+08
A19: =A18+1 -> 16 | B19: ='Networth Inputs - old'!C13 -> Swan Capital | C19: ='Networth Inputs - old'!E13 -> 5881036 | G19: Cash:LBS Ratio will always be 2:1
A20: =A19+1 -> 17 | B20: ='Networth Inputs - old'!C43 -> Sushila Nahar Zerodha | C20: ='Networth Inputs - old'!E43 -> 13500000 | M20: RN Zerodha Cash:
A21: =A20+1 -> 18 | B21: ='Networth Inputs - old'!C44 -> Sumesh FD | C21: ='Networth Inputs - old'!E44 -> 2500000 | M21: Sumesh Stock Buy Value | N21: 23791151
B22: Total | C22: =SUM(C4:C21) -> 7.2828112e+08 | M22: Total CV available for Sumesh | N22: 25000000
M23: Balance cash to keep in RN Zerodha | N23: =N22-N21 -> 1208849
M24: Available cash in RN Zerodha | N24: ='Networth Inputs - old'!E21 -> 14852
A25: Total Debt Exposure for Gold: | M25: Cash Excess/Shortfall | N25: =N24-N23 -> -1193997
C26: ideal gold exposure to cover debt:
A27: =2100*144875 -> 304237500 | C27: =SUMIFS('Networth Inputs - old'!$E$4:$E$54,'Networth Inputs - old'!$D$4:$D$54,"Debt")-'Networth Inputs - old'!E10-'Networth Inputs - old'!E11-'Networth Inputs - old'!E30-'Networth Inputs - old'!E31-'Networth Inputs - old'!E34 -> 1.3821554e+08 | D27: discuss
N30: CURRENT | O30: LOANED | P30: AFTER REVERSAL | R30: Steps:
A31: Total Equity Exposure for Put Protection | M31: Zerodha Broking Mishayan: EQ Holdings | N31: 4654525 | P31: =N31-O31 -> 4654525 | R31: 1. Take 3.15 cr from aurus and pay from RN
M32: Zerodha Broking Mishayan: EQ Mutual Fund | N32: 1.397624e+08 | O32: 1.397624e+08 | P32: =N32-O32 -> 4.7683716e-07 | R32: 2. Buy DMF worth 4.36 cr (can use zerodha cash)
A33: ='Networth Inputs - old'!E19+'Networth Inputs - old'!E20+'Networth Inputs - old'!E24+'Networth Inputs - old'!E25 -> 4.1095882e+08 | M33: Zerodha Broking Mishayan: Debt Mutual Fund | N33: 1.5605863e+08 | O33: 43649885 | P33: =N33-O33 -> 1.1240874e+08 | R33: 3. once dmf is bought and pledged, reverse the loan
M34: Zerodha Broking Mishayan: Liquidbees/ Liquidcase | N34: 20082505 | P34: =N34-O34 -> 20082505 | R34: 4. in tranches buy eq/eqmfs and start reversing loans
A35: Total Exposure for Jay The PM | M35: Zerodha Broking Mishayan: Cash | N35: 1.8642271e+08 | P35: =N35-O35 -> 1.8642271e+08
N36: =SUM(N31:N35) -> 5.0698077e+08 | O36: =SUM(O32:O33) -> 1.8341228e+08 | P36: =SUM(P31:P35) -> 3.2356848e+08
A37: 0 | C37: 60000000 | M37: remove loaned mfs | N37: -1.8341228e+08
N38: =N36+N37 -> 3.2356848e+08
M39: add: aurus deposit | N39: 31500000
M40: total in mishayan | N40: =N38+N39 -> 3.5506848e+08

Sheet Returns and Tax
I1: Total Returns | L1: Total Tax
I2: =SUM(I6:I81) -> #REF! | L2: =SUM(L6:L81) -> #REF!
B5: Sr. No. | C5: Account | D5: Strategy | E5: Portfolio Value | F5: Multiplier | G5: Exposure | H5: Expected Returns % | I5: Returns | J5: Tax Category | K5: Tax Rate | L5: Tax
B6: 1 | C6: Rishabh | D6: Equity Holdings | E6: =GETPIVOTDATA("Value as of Today",'Holdings Summary'!$L$5) -> 1.0744806e+08 | F6: 1 | G6: =E6*F6 -> 1.0744806e+08 | H6: 0.2 | I6: =H6*G6 -> 21489612 | J6: LTCG | K6: 0.125 | L6: =K6*I6 -> 2686201.5
B7: =B6+1 -> 2 | C7: Rishabh | D7: Debt Holdings | E7: 0 | F7: 1 | G7: =E7*F7 -> 0 | H7: 0.06 | I7: =H7*G7 -> 0 | J7: LTCG | K7: 0.3 | L7: =K7*I7 -> 0
B8: =B7+1 -> 3 | C8: Rishabh | D8: Equity Mutual Funds | E8: =GETPIVOTDATA("Value as of Today",'Holdings Summary'!$AE$5,"Debt/Equity","Equity") -> 1.3924535e+08 | F8: 1 | G8: =E8*F8 -> 1.3924535e+08 | H8: 0.2 | I8: =H8*G8 -> 27849070 | J8: LTCG | K8: 0.125 | L8: =K8*I8 -> 3481133.8
B9: =B8+1 -> 4 | C9: Rishabh | D9: Debt Mutual Funds | E9: =GETPIVOTDATA("Value as of Today",'Holdings Summary'!$AE$5,"Debt/Equity","Debt") -> 47626022 | F9: 1 | G9: =E9*F9 -> 47626022 | H9: 0.06 | I9: =H9*G9 -> 2857561.3 | J9: LTCG | K9: 0.3 | L9: =K9*I9 -> 857268.4
B10: =B9+1 -> 5 | C10: Mishayan | D10: Equity Holdings | E10: 0 | F10: 1 | G10: =E10*F10 -> 0 | H10: 0.2 | I10: =H10*G10 -> 0 | J10: LTCG | K10: 0.125 | L10: =K10*I10 -> 0
B11: =B10+1 -> 6 | C11: Mishayan | D11: Debt Holdings | E11: =GETPIVOTDATA("Value as of Today",'Holdings Summary'!$I$5,"Debt/Equity","Debt") -> 20087829 | F11: 1 | G11: =E11*F11 -> 20087829 | H11: 0.06 | I11: =H11*G11 -> 1205269.8 | J11: LTCG | K11: 0.3 | L11: =K11*I11 -> 361580.93
B12: =B11+1 -> 7 | C12: Mishayan | D12: Equity Mutual Funds | E12: =GETPIVOTDATA("Value as of Today",'Holdings Summary'!$AA$5,"Debt/Equity","Equity") -> #REF! | F12: 1 | G12: =E12*F12 -> #REF! | H12: 0.2 | I12: =H12*G12 -> #REF! | J12: LTCG | K12: 0.125 | L12: =K12*I12 -> #REF!
B13: =B12+1 -> 8 | C13: Mishayan | D13: Debt Mutual Funds | E13: =GETPIVOTDATA("Value as of Today",'Holdings Summary'!$AA$5,"Debt/Equity","Debt") -> 92406491 | F13: 1 | G13: =E13*F13 -> 92406491 | H13: 0.06 | I13: =H13*G13 -> 5544389.4 | J13: LTCG | K13: 0.25 | L13: =K13*I13 -> 1386097.4
B14: =B13+1 -> 9 | C14: Mishayan | D14: ='Strategy Allocation Old'!B5&" "&'Strategy Allocation Old'!C5 -> Mishayan Zerodha Client Account Long Options | E14: ='Strategy Allocation Old'!E5 -> 7.2828112e+08 | F14: ='Strategy Allocation Old'!D5 -> 0.015 | G14: ='Strategy Allocation Old'!F5 -> 7.2828112e+08 | H14: 0.1 | I14: =H14*G14 -> 72828112 | J14: FnO | K14: 0.25 | L14: =K14*I14 -> 18207028
B15: =B14+1 -> 10 | C15: Mishayan | D15: ='Strategy Allocation Old'!B6&" "&'Strategy Allocation Old'!C6 -> Mishayan Zerodha Client Account PSAR | E15: ='Strategy Allocation Old'!E6 -> 7.2828112e+08 | F15: ='Strategy Allocation Old'!D6 -> 2.12 | G15: ='Strategy Allocation Old'!F6 -> 1.543956e+09 | H15: 0.2 | I15: =H15*G15 -> 3.0879119e+08 | J15: FnO | K15: 0.25 | L15: =K15*I15 -> 77197799
B16: =B15+1 -> 11 | C16: Mishayan | D16: ='Strategy Allocation Old'!B7&" "&'Strategy Allocation Old'!C7 -> Mishayan Zerodha Client Account Gold | E16: ='Strategy Allocation Old'!E7 -> 304237500 | F16: ='Strategy Allocation Old'!D7 -> 1 | G16: ='Strategy Allocation Old'!F7 -> 304237500 | H16: 0.1 | I16: =H16*G16 -> 30423750 | J16: FnO | K16: 0.25 | L16: =K16*I16 -> 7605937.5
B17: =B16+1 -> 12 | C17: Mishayan | D17: ='Strategy Allocation Old'!B8&" "&'Strategy Allocation Old'!C8 -> Mishayan Zerodha Client Account Put Protection | E17: ='Strategy Allocation Old'!E8 -> 4.1095882e+08 | F17: ='Strategy Allocation Old'!D8 -> 1 | G17: ='Strategy Allocation Old'!F8 -> 4.1095882e+08 | H17: -0.02 | I17: =H17*G17 -> -8219176.4 | J17: FnO | K17: 0.25 | L17: =K17*I17 -> -2054794.1
B18: =B17+1 -> 13 | C18: Mishayan | D18: ='Strategy Allocation Old'!B9&" "&'Strategy Allocation Old'!C9 -> Mishayan Zerodha Client Account Stock Futures | E18: ='Strategy Allocation Old'!E9 -> 0 | F18: ='Strategy Allocation Old'!D9 -> 1 | G18: ='Strategy Allocation Old'!F9 -> 0 | H18: 0.1 | I18: =H18*G18 -> 0 | J18: FnO | K18: 0.25 | L18: =K18*I18 -> 0
B19: =B18+1 -> 14 | C19: Rishabh | D19: ='Strategy Allocation Old'!B10&" "&'Strategy Allocation Old'!C10 -> SRE Long Options | E19: ='Strategy Allocation Old'!E10 -> 116820000 | F19: ='Strategy Allocation Old'!D10 -> 0.015 | G19: ='Strategy Allocation Old'!F10 -> 116820000 | H19: 0.1 | I19: =H19*G19 -> 11682000 | J19: FnO | K19: 0.3 | L19: =K19*I19 -> 3504600
B20: =B19+1 -> 15 | C20: Rishabh | D20: ='Strategy Allocation Old'!B11&" "&'Strategy Allocation Old'!C11 -> SRE PSAR | E20: ='Strategy Allocation Old'!E11 -> 116820000 | F20: ='Strategy Allocation Old'!D11 -> 2 | G20: ='Strategy Allocation Old'!F11 -> 233640000 | H20: 0.1 | I20: =H20*G20 -> 23364000 | J20: FnO | K20: 0.3 | L20: =K20*I20 -> 7009200
B21: =B20+1 -> 16 | C21: Rishabh | D21: ='Strategy Allocation Old'!B12&" "&'Strategy Allocation Old'!C12 -> Aurus Alpha Long Options | E21: ='Strategy Allocation Old'!E12 -> 249427750 | F21: ='Strategy Allocation Old'!D12 -> 0.025 | G21: ='Strategy Allocation Old'!F12 -> 249427750 | H21: 0.1 | I21: =H21*G21 -> 24942775 | J21: FnO | K21: 0.3 | L21: =K21*I21 -> 7482832.5
B22: =B21+1 -> 17 | C22: Rishabh | D22: ='Strategy Allocation Old'!B13&" "&'Strategy Allocation Old'!C13 -> Aurus Alpha PSAR | E22: ='Strategy Allocation Old'!E13 -> 249427750 | F22: ='Strategy Allocation Old'!D13 -> 3.34 | G22: ='Strategy Allocation Old'!F13 -> 833088685 | H22: 0.1 | I22: =H22*G22 -> 83308868 | J22: FnO | K22: 0.3 | L22: =K22*I22 -> 24992661
B23: =B22+1 -> 18 | C23: Rishabh | D23: ='Strategy Allocation Old'!B14&" "&'Strategy Allocation Old'!C14 -> Marwadi Long Options | E23: ='Strategy Allocation Old'!E14 -> 227306000 | F23: ='Strategy Allocation Old'!D14 -> 0.015 | G23: ='Strategy Allocation Old'!F14 -> 227306000 | H23: 0.1 | I23: =H23*G23 -> 22730600 | J23: FnO | K23: 0.3 | L23: =K23*I23 -> 6819180
B24: =B23+1 -> 19 | C24: Rishabh | D24: ='Strategy Allocation Old'!B15&" "&'Strategy Allocation Old'!C15 -> Marwadi PSAR | E24: ='Strategy Allocation Old'!E15 -> 227306000 | F24: ='Strategy Allocation Old'!D15 -> 3 | G24: ='Strategy Allocation Old'!F15 -> 681918000 | H24: 0.1 | I24: =H24*G24 -> 68191800 | J24: FnO | K24: 0.3 | L24: =K24*I24 -> 20457540
B25: =B24+1 -> 20 | C25: Rishabh | D25: ='Strategy Allocation Old'!B16&" "&'Strategy Allocation Old'!C16 -> Marwadi Gold Futures | E25: ='Strategy Allocation Old'!E16 -> 90922400 | F25: ='Strategy Allocation Old'!D16 -> 1 | G25: ='Strategy Allocation Old'!F16 -> 90922400 | H25: 0.1 | I25: =H25*G25 -> 9092240 | J25: FnO | K25: 0.3 | L25: =K25*I25 -> 2727672
... B55: =B54+1 -> 50 | C55: Rishabh | D55: ='Strategy Allocation Old'!B46&" "&'Strategy Allocation Old'!C46 | E55: ='Strategy Allocation Old'!E46 -> 0 | F55: ='Strategy Allocation Old'!D46 -> 0 | G55: ='Strategy Allocation Old'!F46 -> 0 | H55: 0.1 | I55: =H55*G55 -> 0 | J55: FnO | K55: 0.3 | L55: =K55*I55 -> 0
